{"schema_version": 1, "records": [{"ts": 1784270436.7566574, "symbol": "O", "direction": "long", "entry_lo": 0.57773227, "entry_hi": 0.58240107, "sl": 0.56328896, "tp1": 0.589125, "tp2": 0.5973, "tp3": 0.60523333, "rr_tp1_live": 0.35, "shadow_rr_gate_pass": false, "breaker_mitigation": "mitigation", "divergence": {"bearish_classical": false, "bearish_hidden": false, "bullish_classical": false, "bullish_hidden": true}, "bpr_zone_count": 5, "bpr_confluence": false, "whale_klvl_confluence": false, "whale_klvl_matches": [], "amd_phase_methodology": {"phase": "manipulation_bear", "nymidnight_price": 0.5836, "price_vs_nymidnight": "below"}, "inducement": {"inducement_swept": true, "detail": {"type": "sweep_high", "level": 0.5669, "bars_ago": 13, "volume_confirmed": false}}, "order_block_live": {"bull": false, "bull_zone": null, "bear": false, "bear_zone": null}, "order_block_methodology": {"bull": false, "bull_zone": null, "bear": false, "bear_zone": null}, "chart_patterns": {"flag": {"bull": true, "bear": false, "target": 0.7525}, "head_shoulders": {"top": true, "bottom": false, "target": 0.4290999999999999}, "triangle": {"type": "descending"}}, "patches_affected": ["02-rr-gate", "03-breaker-mitigation"], "discrepancy": ["rr_gate: R:R 0.35 прошёл live-гейт (1.5), но НЕ прошёл бы shadow-гейт (2.0)"], "live_journal_id": null, "tz13_shadow": {"ok": true, "block1_bias": {"bias": "SHORT", "structure_1d": "LH/LL (даунтренд)", "tf_agreement": "1D задаёт направление, 4H EMA не подтверждает явно", "detail": ["1D структура: LH/LL (даунтренд)", "4H EMA-стек: смешанный", "1H EMA-стек (контекст входа): недостаточно данных", "Ключевой минимум: 0.4724 (пробой = предпосылка разворота/продолжения вниз)", "Ключевой хай: 0.6057 (снятие = цель движения вверх)"], "key_low": {"price": 0.4724, "bars_ago": 4}, "key_high": {"price": 0.6057, "bars_ago": 6}}, "block2_elliott": {"elliott_1d": {"wave": null, "label": "волна не определена", "note": "структура неоднозначная", "score_delta": 0}, "elliott_4h": {"wave": null, "label": "волна не определена", "note": "структура неоднозначная", "score_delta": 0}}, "block3_setup_type": {"setup_type": "AMD", "label": "AMD — фаза manipulation_bear (цена below NY-midnight)", "detail": {"phase": "manipulation_bear", "nymidnight_price": 0.5836, "price_vs_nymidnight": "below"}}, "block4_zones": {"above": [{"lo": 0.5865, "hi": 0.5914593999999999, "mid": 0.5891249999999999, "touches": 4, "hours_ago": 39, "sources": ["1h", "4h"]}, {"lo": 0.5949656, "hi": 0.5996343999999999, "mid": 0.5972999999999999, "touches": 2, "hours_ago": 184, "sources": ["4h"]}, {"lo": 0.6028989333333334, "hi": 0.6075677333333334, "mid": 0.6052333333333334, "touches": 3, "hours_ago": 140, "sources": ["1d", "4h"]}, {"lo": 0.6210656, "hi": 0.6257343999999999, "mid": 0.6234, "touches": 2, "hours_ago": 428, "sources": ["1d", "4h"]}, {"lo": 0.6804656, "hi": 0.6851343999999999, "mid": 0.6828, "touches": 2, "hours_ago": 296, "sources": ["1d", "4h"]}], "below": [{"lo": 0.5777322666666667, "hi": 0.5824010666666666, "mid": 0.5800666666666666, "touches": 3, "hours_ago": 43, "sources": ["1h", "4h"]}, {"lo": 0.5657, "hi": 0.5736, "mid": 0.56962, "touches": 5, "hours_ago": 30, "sources": ["1h", "4h"]}, {"lo": 0.5617882209149395, "hi": 0.5664570209149394, "mid": 0.5641226209149395, "touches": 1, "hours_ago": 0, "sources": ["ema"]}, {"lo": 0.5525989333333334, "hi": 0.5577, "mid": 0.5549333333333334, "touches": 3, "hours_ago": 32, "sources": ["1h", "4h"]}, {"lo": 0.5519562455376992, "hi": 0.5566250455376991, "mid": 0.5542906455376991, "touches": 1, "hours_ago": 0, "sources": ["ema"]}, {"lo": 0.550512441215637, "hi": 0.555181241215637, "mid": 0.552846841215637, "touches": 1, "hours_ago": 0, "sources": ["ema"]}, {"lo": 0.5435989333333334, "hi": 0.5482677333333333, "mid": 0.5459333333333334, "touches": 3, "hours_ago": 15, "sources": ["1h", "4h"]}, {"lo": 0.5154, "hi": 0.537, "mid": 0.5249727272727273, "touches": 11, "hours_ago": 8, "sources": ["1d", "1h", "4h"]}, {"lo": 0.4994656, "hi": 0.5041344, "mid": 0.5018, "touches": 2, "hours_ago": 300, "sources": ["4h"]}, {"lo": 0.4702, "hi": 0.4789, "mid": 0.47416, "touches": 5, "hours_ago": 88, "sources": ["1d", "4h"]}, {"lo": 0.45966559999999995, "hi": 0.4643344, "mid": 0.46199999999999997, "touches": 2, "hours_ago": 432, "sources": ["4h"]}, {"lo": 0.38046559999999996, "hi": 0.3851344, "mid": 0.3828, "touches": 2, "hours_ago": 480, "sources": ["1d", "4h"]}]}, "block5_checklist": {"items": [["Тренд старшего ТФ (1D) совпадает с направлением", true], ["Свежий свип ликвидности в пользу направления", false], ["Цена у зоны интереса (не в вакууме)", true], ["Killzone активна или близко", true], ["Funding не против позиции", true], ["R:R по структуре ≥ 1:1.5", false]], "score": 4}, "block6_liquidity": {"sweep_1h": null, "sweep_4h": {"type": "sweep_high", "level": 0.5669, "bars_ago": 13, "volume_confirmed": false}, "equal_levels": [{"price": 0.5792999999999999, "kind": "high", "touches": 2}, {"price": 0.59, "kind": "high", "touches": 2}, {"price": 0.605, "kind": "high", "touches": 2}, {"price": 0.5155, "kind": "low", "touches": 2}, {"price": 0.53155, "kind": "low", "touches": 2}, {"price": 0.54645, "kind": "low", "touches": 2}]}, "block7_oi": {"oi_change_pct": 0.0, "oi_combo": null, "funding": null, "ls_ratio": 1.13}, "block8_killzone": {"active": {"name": "🇬🇧 Лондон Open", "start": 540, "end": 720, "quality": "A+", "desc": "Наибольшие объёмы дня, ищем хай/лоу дня", "remaining_min": 141}, "next": {"name": "🇺🇸 NY Open", "start": 840, "end": 1020, "quality": "A", "desc": "Продолжение дневного диапазона, часто коррекция после Лондона", "in_min": 261}, "is_good": true, "hour": 9, "all_zones": [{"name": "🌏 Азиатская сессия", "start": 0, "end": 480, "quality": "B", "desc": "Низкая волатильность, часто рендж или хай/лоу дня"}, {"name": "🇬🇧 Лондон Open", "start": 540, "end": 720, "quality": "A+", "desc": "Наибольшие объёмы дня, ищем хай/лоу дня", "remaining_min": 141}, {"name": "🇺🇸 NY Open", "start": 840, "end": 1020, "quality": "A", "desc": "Продолжение дневного диапазона, часто коррекция после Лондона"}, {"name": "🇬🇧 Лондон Close", "start": 1020, "end": 1140, "quality": "B", "desc": "Закрытие Лондона -- два источника, точная граница расходится (см. докстринг)"}, {"name": "🇺🇸 NY Close", "start": 1380, "end": 1440, "quality": "C", "desc": "Закрытие Нью-Йорка, не подтверждено источником"}]}, "block9_phase": {"phase": "переходная/не определена", "note": "объём: доступен, но не используется в этой упрощённой эвристике"}, "block10_dca": {"entry1": 0.5865, "entry2": 0.5889796999999999, "entry3": 0.5914593999999999, "weights": "50/30/20"}, "block11_tp_rr": {"tp1": 0.5800666666666666, "tp2": 0.56962, "tp3": 0.5641226209149395, "rr_tp1": 0.33, "rr_tp2": 0.85, "rr_tp3": 1.13, "rr_gate_pass": false}, "block12_sl": {"sl": 0.6062458849999998, "buffer_pct": 2.5}, "block13_verdict": {"has_setup": false, "direction": "short", "score": 4, "text": "шорт: сетапа нет (чеклист 4/6), тип сетапа: AMD — фаза manipulation_bear (цена below NY-midnight)"}, "direction": "short", "score": 4, "entry_zone": {"lo": 0.5865, "hi": 0.5914593999999999}, "sl": 0.6062458849999998, "tp1": 0.5800666666666666, "tp2": 0.56962, "tp3": 0.5641226209149395, "setup_type": "AMD"}, "tz13_score": 4, "tz13_direction": "short", "tz13_setup_type": "AMD", "tz13_entry_zone": {"lo": 0.5865, "hi": 0.5914593999999999}, "tz13_sl": 0.6062458849999998, "tz13_tp1": 0.5800666666666666, "tz13_tp2": 0.56962, "tz13_tp3": 0.5641226209149395, "sweep_1h": null, "sweep_4h": {"type": "sweep_high", "level": 0.5669, "bars_ago": 13, "volume_confirmed": false}, "source": "send_scheduled", "promoted_live": false, "gate_reasons": ["rocket_or_grade", "rr_gate"], "oi_funding_ls_shadow": {"oi_change_pct": 0.0, "oi_combo": null, "funding_rate": 0.036813, "ls_ratio": 1.13, "d_oi": 0, "d_funding": 0, "d_ls": 0, "total_delta": 0, "rocket_old": 44, "rocket_would_be": 44}, "bos_body_close_shadow": {"wick_only_type": "BOS_bull", "body_close_type": "invalid_break_wick_only", "disagree": true, "downgraded_to_invalid": true, "body_close_label": "Пробой вверх только тенью, без закрытия за уровнем 0.5865 -- по критерию \"Урок 2. Structure\" это SFP, не валидный слом структуры"}, "order_block_shadow": {"live": {"bull": false, "bull_zone": null, "bear": false, "bear_zone": null}, "methodology": {"bull": false, "bull_zone": null, "bear": false, "bear_zone": null}}}, {"ts": 1784270469.7696617, "symbol": "SENTIS", "direction": "long", "entry_lo": 0.188762, "entry_hi": 0.188762, "sl": 0.18309914, "tp1": 0.19253724, "tp2": 0.19487034, "tp3": 0.19864558, "rr_tp1_live": 0.67, "shadow_rr_gate_pass": false, "breaker_mitigation": null, "divergence": {}, "bpr_zone_count": 0, "bpr_confluence": false, "whale_klvl_confluence": false, "whale_klvl_matches": [], "amd_phase_methodology": {"phase": "manipulation", "nymidnight_price": null, "price_vs_nymidnight": null}, "inducement": {"inducement_swept": false, "detail": null}, "order_block_live": {"bull": false, "bull_zone": null, "bear": false, "bear_zone": null}, "order_block_methodology": {"bull": false, "bull_zone": null, "bear": false, "bear_zone": null}, "chart_patterns": {"flag": {"bull": false, "bear": false, "target": null}, "head_shoulders": {"top": false, "bottom": false, "target": null}, "triangle": {"type": null}}, "patches_affected": ["02-rr-gate"], "discrepancy": ["rr_gate: R:R 0.67 прошёл live-гейт (1.5), но НЕ прошёл бы shadow-гейт (2.0)"], "live_journal_id": null, "tz13_shadow": {"ok": false, "error": "нет 4h-свечей"}, "tz13_score": null, "tz13_direction": null, "tz13_setup_type": null, "tz13_entry_zone": null, "tz13_sl": null, "tz13_tp1": null, "tz13_tp2": null, "tz13_tp3": null, "sweep_1h": null, "sweep_4h": null, "source": "send_scheduled", "promoted_live": false, "gate_reasons": ["rocket_or_grade", "rr_gate"], "oi_funding_ls_shadow": {"oi_change_pct": 0.0, "oi_combo": null, "funding_rate": null, "ls_ratio": 1.0, "d_oi": 0, "d_funding": 0, "d_ls": 0, "total_delta": 0, "rocket_old": 30, "rocket_would_be": 30}, "bos_body_close_shadow": {"wick_only_type": null, "body_close_type": null, "disagree": false, "downgraded_to_invalid": false, "body_close_label": "н/д -- нет 4h-свечей"}, "order_block_shadow": {"error": "нет 4h-свечей"}}, {"ts": 1784270475.1208344, "symbol": "GRAM", "direction": "short", "entry_lo": 1.476136, "entry_hi": 1.487664, "sl": 1.5248556, "tp1": 1.3786968, "tp2": 1.32023328, "tp3": 1.232538, "rr_tp1_live": 2.0, "shadow_rr_gate_pass": true, "breaker_mitigation": "mitigation", "divergence": {"bearish_classical": false, "bearish_hidden": false, "bullish_classical": true, "bullish_hidden": false}, "bpr_zone_count": 1, "bpr_confluence": false, "whale_klvl_confluence": false, "whale_klvl_matches": [], "amd_phase_methodology": {"phase": "manipulation_bear", "nymidnight_price": 1.441, "price_vs_nymidnight": "below"}, "inducement": {"inducement_swept": true, "detail": {"type": "sweep_low", "level": 1.55, "bars_ago": 4, "volume_confirmed": false}}, "order_block_live": {"bull": false, "bull_zone": null, "bear": false, "bear_zone": null}, "order_block_methodology": {"bull": false, "bull_zone": null, "bear": false, "bear_zone": null}, "chart_patterns": {"flag": {"bull": false, "bear": true, "target": 1.3608000000000002}, "head_shoulders": {"top": true, "bottom": false, "target": 1.5589}, "triangle": {"type": null}}, "patches_affected": ["03-breaker-mitigation", "04-rsi-divergence"], "discrepancy": ["divergence: классическая дивергенция ПРОТИВ направления сигнала"], "live_journal_id": null, "tz13_shadow": {"ok": true, "block1_bias": {"bias": "SHORT", "structure_1d": "смешанная (микс HH/LL)", "tf_agreement": "4H EMA задаёт направление, 1D структура не подтверждает явно", "detail": ["1D структура: смешанная (микс HH/LL)", "4H EMA-стек: медвежий", "1H EMA-стек (контекст входа): недостаточно данных", "Ключевой минимум: 1.5475 (пробой = предпосылка разворота/продолжения вниз)", "Ключевой хай: 1.6991 (снятие = цель движения вверх)"], "key_low": {"price": 1.5475, "bars_ago": 9}, "key_high": {"price": 1.6991, "bars_ago": 6}}, "block2_elliott": {"elliott_1d": {"wave": null, "label": "волна не определена", "note": "структура неоднозначная", "score_delta": 0}, "elliott_4h": {"wave": null, "label": "волна не определена", "note": "структура неоднозначная", "score_delta": 0}}, "block3_setup_type": {"setup_type": "SH-BOS-RTO", "label": "SH-BOS-RTO — свип sweep_low (4 баров назад) + BOS — пробой структуры вниз по тренду (согласовано с bias SHORT)", "detail": {"sweep": {"type": "sweep_low", "level": 1.55, "bars_ago": 4, "volume_confirmed": false}, "bos": {"type": "BOS_bear", "label": "BOS — пробой структуры вниз по тренду (согласовано с bias SHORT)", "aligned": true}}}, "block4_zones": {"above": [{"lo": 1.476136, "hi": 1.487664, "mid": 1.4819, "touches": 2, "hours_ago": 392, "sources": ["1d", "4h"]}, {"lo": 1.5171, "hi": 1.5637, "mid": 1.54271, "touches": 20, "hours_ago": 5, "sources": ["1d", "1h", "4h"]}, {"lo": 1.5781, "hi": 1.5976, "mid": 1.587525, "touches": 8, "hours_ago": 25, "sources": ["1h", "4h"]}, {"lo": 1.5925939756518668, "hi": 1.604121975651867, "mid": 1.5983579756518669, "touches": 1, "hours_ago": 0, "sources": ["ema"]}, {"lo": 1.6133014379529558, "hi": 1.624829437952956, "mid": 1.6190654379529559, "touches": 1, "hours_ago": 0, "sources": ["ema"]}, {"lo": 1.614, "hi": 1.6348, "mid": 1.6278090909090908, "touches": 11, "hours_ago": 42, "sources": ["1d", "1h", "4h"]}, {"lo": 1.6259840345255532, "hi": 1.6375120345255534, "mid": 1.6317480345255533, "touches": 1, "hours_ago": 0, "sources": ["ema"]}, {"lo": 1.6463109999999999, "hi": 1.6605, "mid": 1.652075, "touches": 4, "hours_ago": 64, "sources": ["4h"]}, {"lo": 1.693119333333333, "hi": 1.7046473333333332, "mid": 1.698883333333333, "touches": 6, "hours_ago": 144, "sources": ["1d", "4h"]}, {"lo": 1.8031359999999999, "hi": 1.814664, "mid": 1.8089, "touches": 2, "hours_ago": 252, "sources": ["4h"]}, {"lo": 1.836836, "hi": 1.8483640000000001, "mid": 1.8426, "touches": 2, "hours_ago": 304, "sources": ["1d", "4h"]}], "below": []}, "block5_checklist": {"items": [["Тренд старшего ТФ (1D) совпадает с направлением", false], ["Свежий свип ликвидности в пользу направления", false], ["Цена у зоны интереса (не в вакууме)", false], ["Killzone активна или близко", true], ["Funding не против позиции", true], ["R:R по структуре ≥ 1:1.5", true]], "score": 3}, "block6_liquidity": {"sweep_1h": null, "sweep_4h": {"type": "sweep_low", "level": 1.55, "bars_ago": 4, "volume_confirmed": false}, "equal_levels": [{"price": 1.62815, "kind": "high", "touches": 4}, {"price": 1.7023, "kind": "high", "touches": 3}, {"price": 1.8089, "kind": "high", "touches": 2}, {"price": 1.5179999999999998, "kind": "low", "touches": 2}, {"price": 1.524, "kind": "low", "touches": 2}, {"price": 1.541325, "kind": "low", "touches": 4}, {"price": 1.5496666666666667, "kind": "low", "touches": 3}, {"price": 1.6335, "kind": "low", "touches": 3}]}, "block7_oi": {"oi_change_pct": -0.4729639441933696, "oi_combo": "down_down", "funding": null, "ls_ratio": 2.95}, "block8_killzone": {"active": {"name": "🇬🇧 Лондон Open", "start": 540, "end": 720, "quality": "A+", "desc": "Наибольшие объёмы дня, ищем хай/лоу дня", "remaining_min": 139}, "next": {"name": "🇺🇸 NY Open", "start": 840, "end": 1020, "quality": "A", "desc": "Продолжение дневного диапазона, часто коррекция после Лондона", "in_min": 259}, "is_good": true, "hour": 9, "all_zones": [{"name": "🌏 Азиатская сессия", "start": 0, "end": 480, "quality": "B", "desc": "Низкая волатильность, часто рендж или хай/лоу дня"}, {"name": "🇬🇧 Лондон Open", "start": 540, "end": 720, "quality": "A+", "desc": "Наибольшие объёмы дня, ищем хай/лоу дня", "remaining_min": 139}, {"name": "🇺🇸 NY Open", "start": 840, "end": 1020, "quality": "A", "desc": "Продолжение дневного диапазона, часто коррекция после Лондона"}, {"name": "🇬🇧 Лондон Close", "start": 1020, "end": 1140, "quality": "B", "desc": "Закрытие Лондона -- два источника, точная граница расходится (см. докстринг)"}, {"name": "🇺🇸 NY Close", "start": 1380, "end": 1440, "quality": "C", "desc": "Закрытие Нью-Йорка, не подтверждено источником"}]}, "block9_phase": {"phase": "Накопление (Accumulation)", "note": "объём: доступен, но не используется в этой упрощённой эвристике"}, "block10_dca": {"entry1": 1.476136, "entry2": 1.4819, "entry3": 1.487664, "weights": "50/30/20"}, "block11_tp_rr": {"tp1": 1.3786967999999997, "tp2": 1.3202332799999996, "tp3": 1.2325379999999995, "rr_tp1": 2.0, "rr_tp2": 3.2, "rr_tp3": 5.0, "rr_gate_pass": true}, "block12_sl": {"sl": 1.5248556, "buffer_pct": 2.5}, "block13_verdict": {"has_setup": false, "direction": "short", "score": 3, "text": "шорт: сетапа нет (чеклист 3/6), тип сетапа: SH-BOS-RTO — свип sweep_low (4 баров назад) + BOS — пробой структуры вниз по тренду (согласовано с bias SHORT)"}, "direction": "short", "score": 3, "entry_zone": {"lo": 1.476136, "hi": 1.487664}, "sl": 1.5248556, "tp1": 1.3786967999999997, "tp2": 1.3202332799999996, "tp3": 1.2325379999999995, "setup_type": "SH-BOS-RTO"}, "tz13_score": 3, "tz13_direction": "short", "tz13_setup_type": "SH-BOS-RTO", "tz13_entry_zone": {"lo": 1.476136, "hi": 1.487664}, "tz13_sl": 1.5248556, "tz13_tp1": 1.3786967999999997, "tz13_tp2": 1.3202332799999996, "tz13_tp3": 1.2325379999999995, "sweep_1h": null, "sweep_4h": {"type": "sweep_low", "level": 1.55, "bars_ago": 4, "volume_confirmed": false}, "source": "send_scheduled", "promoted_live": false, "gate_reasons": ["rsi_extreme_short", "rocket_or_grade"], "oi_funding_ls_shadow": {"oi_change_pct": -0.4729639441933696, "oi_combo": "down_down", "funding_rate": -0.04143, "ls_ratio": 2.95, "d_oi": 2, "d_funding": 0, "d_ls": 3, "total_delta": 5, "rocket_old": 43, "rocket_would_be": 48}, "bos_body_close_shadow": {"wick_only_type": "BOS_bear", "body_close_type": "invalid_break_wick_only", "disagree": true, "downgraded_to_invalid": true, "body_close_label": "Пробой вниз только тенью, без закрытия за уровнем 1.5573 -- по критерию \"Урок 2. Structure\" это SFP, не валидный слом структуры"}, "order_block_shadow": {"live": {"bull": false, "bull_zone": null, "bear": false, "bear_zone": null}, "methodology": {"bull": false, "bull_zone": null, "bear": false, "bear_zone": null}}}, {"ts": 1784270479.5373046, "symbol": "ASTER", "direction": "short", "entry_lo": 0.62499102, "entry_hi": 0.62886602, "sl": 0.64458768, "tp1": 0.59025, "tp2": 0.5839, "tp3": 0.52700777, "rr_tp1_live": 1.77, "shadow_rr_gate_pass": false, "breaker_mitigation": "mitigation", "divergence": {"bearish_classical": false, "bearish_hidden": true, "bullish_classical": false, "bullish_hidden": false}, "bpr_zone_count": 6, "bpr_confluence": false, "whale_klvl_confluence": false, "whale_klvl_matches": [], "amd_phase_methodology": {"phase": "manipulation_bear", "nymidnight_price": 0.6141, "price_vs_nymidnight": "below"}, "inducement": {"inducement_swept": true, "detail": {"type": "sweep_low", "level": 0.6252, "bars_ago": 4, "volume_confirmed": true}}, "order_block_live": {"bull": false, "bull_zone": null, "bear": false, "bear_zone": null}, "order_block_methodology": {"bull": false, "bull_zone": null, "bear": false, "bear_zone": null}, "chart_patterns": {"flag": {"bull": false, "bear": true, "target": 0.43309999999999993}, "head_shoulders": {"top": true, "bottom": false, "target": 0.6085}, "triangle": {"type": "descending"}}, "patches_affected": ["02-rr-gate", "03-breaker-mitigation"], "discrepancy": ["rr_gate: R:R 1.77 прошёл live-гейт (1.5), но НЕ прошёл бы shadow-гейт (2.0)"], "live_journal_id": null, "tz13_shadow": {"ok": true, "block1_bias": {"bias": "NEUTRAL", "structure_1d": "HH/HL (аптренд)", "tf_agreement": "1D и 4H расходятся", "detail": ["1D структура: HH/HL (аптренд)", "4H EMA-стек: медвежий", "1H EMA-стек (контекст входа): недостаточно данных", "Ключевой минимум: 0.6136 (пробой = предпосылка разворота/продолжения вниз)", "Ключевой хай: 0.642 (снятие = цель движения вверх)"], "key_low": {"price": 0.6136, "bars_ago": 4}, "key_high": {"price": 0.642, "bars_ago": 3}}, "block2_elliott": {"elliott_1d": {"wave": null, "label": "волна не определена", "note": "структура неоднозначная", "score_delta": 0}, "elliott_4h": {"wave": null, "label": "волна не определена", "note": "структура неоднозначная", "score_delta": 0}}, "block3_setup_type": {"setup_type": "AMD", "label": "AMD — фаза manipulation_bear (цена below NY-midnight)", "detail": {"phase": "manipulation_bear", "nymidnight_price": 0.6141, "price_vs_nymidnight": "below"}}, "block4_zones": {"above": [{"lo": 0.6249910248424975, "hi": 0.6288660248424975, "mid": 0.6269285248424975, "touches": 1, "hours_ago": 0, "sources": ["ema"]}, {"lo": 0.6141, "hi": 0.6489, "mid": 0.627169014084507, "touches": 71, "hours_ago": 5, "sources": ["1d", "1h", "4h"]}, {"lo": 0.6268556788793267, "hi": 0.6307306788793268, "mid": 0.6287931788793267, "touches": 1, "hours_ago": 0, "sources": ["ema"]}, {"lo": 0.6294313325246456, "hi": 0.6333063325246456, "mid": 0.6313688325246456, "touches": 1, "hours_ago": 0, "sources": ["ema"]}, {"lo": 0.6526424999999999, "hi": 0.6565175, "mid": 0.6545799999999999, "touches": 5, "hours_ago": 300, "sources": ["1d", "4h"]}, {"lo": 0.6762125, "hi": 0.6800875000000001, "mid": 0.67815, "touches": 2, "hours_ago": 724, "sources": ["4h"]}, {"lo": 0.8023625, "hi": 0.8062375, "mid": 0.8043, "touches": 2, "hours_ago": 708, "sources": ["1d", "4h"]}], "below": [{"lo": 0.5883124999999999, "hi": 0.5921875, "mid": 0.5902499999999999, "touches": 2, "hours_ago": 520, "sources": ["1d", "4h"]}, {"lo": 0.5819624999999999, "hi": 0.5858375, "mid": 0.5839, "touches": 2, "hours_ago": 540, "sources": ["1d", "4h"]}]}, "block5_checklist": {"items": [["Тренд старшего ТФ (1D) совпадает с направлением", false], ["Свежий свип ликвидности в пользу направления", false], ["Цена у зоны интереса (не в вакууме)", false], ["Killzone активна или близко", true], ["Funding не против позиции", true], ["R:R по структуре ≥ 1:1.5", false]], "score": 2}, "block6_liquidity": {"sweep_1h": null, "sweep_4h": {"type": "sweep_low", "level": 0.6252, "bars_ago": 4, "volume_confirmed": true}, "equal_levels": [{"price": 0.62515, "kind": "high", "touches": 4}, {"price": 0.6338142857142858, "kind": "high", "touches": 7}, {"price": 0.64126, "kind": "high", "touches": 5}, {"price": 0.6454500000000001, "kind": "high", "touches": 2}, {"price": 0.6484666666666666, "kind": "high", "touches": 3}, {"price": 0.6541999999999999, "kind": "high", "touches": 3}, {"price": 0.67815, "kind": "high", "touches": 2}, {"price": 0.6200666666666668, "kind": "low", "touches": 24}, {"price": 0.6319, "kind": "low", "touches": 2}]}, "block7_oi": {"oi_change_pct": 0.18909107072861414, "oi_combo": "down_up", "funding": null, "ls_ratio": 2.44}, "block8_killzone": {"active": {"name": "🇬🇧 Лондон Open", "start": 540, "end": 720, "quality": "A+", "desc": "Наибольшие объёмы дня, ищем хай/лоу дня", "remaining_min": 139}, "next": {"name": "🇺🇸 NY Open", "start": 840, "end": 1020, "quality": "A", "desc": "Продолжение дневного диапазона, часто коррекция после Лондона", "in_min": 259}, "is_good": true, "hour": 9, "all_zones": [{"name": "🌏 Азиатская сессия", "start": 0, "end": 480, "quality": "B", "desc": "Низкая волатильность, часто рендж или хай/лоу дня"}, {"name": "🇬🇧 Лондон Open", "start": 540, "end": 720, "quality": "A+", "desc": "Наибольшие объёмы дня, ищем хай/лоу дня", "remaining_min": 139}, {"name": "🇺🇸 NY Open", "start": 840, "end": 1020, "quality": "A", "desc": "Продолжение дневного диапазона, часто коррекция после Лондона"}, {"name": "🇬🇧 Лондон Close", "start": 1020, "end": 1140, "quality": "B", "desc": "Закрытие Лондона -- два источника, точная граница расходится (см. докстринг)"}, {"name": "🇺🇸 NY Close", "start": 1380, "end": 1440, "quality": "C", "desc": "Закрытие Нью-Йорка, не подтверждено источником"}]}, "block9_phase": {"phase": "Накопление (Accumulation)", "note": "объём: доступен, но не используется в этой упрощённой эвристике"}, "block10_dca": {"entry1": null, "entry2": null, "entry3": null, "weights": "50/30/20"}, "block11_tp_rr": {"tp1": null, "tp2": null, "tp3": null, "rr_tp1": null, "rr_tp2": null, "rr_tp3": null, "rr_gate_pass": false}, "block12_sl": {"sl": null, "buffer_pct": 2.5}, "block13_verdict": {"has_setup": false, "direction": null, "score": 2, "text": "направление не определено (1D/4H не согласованы)"}, "direction": null, "score": 2, "entry_zone": null, "sl": null, "tp1": null, "tp2": null, "tp3": null, "setup_type": "AMD"}, "tz13_score": 2, "tz13_direction": null, "tz13_setup_type": "AMD", "tz13_entry_zone": null, "tz13_sl": null, "tz13_tp1": null, "tz13_tp2": null, "tz13_tp3": null, "sweep_1h": null, "sweep_4h": {"type": "sweep_low", "level": 0.6252, "bars_ago": 4, "volume_confirmed": true}, "source": "send_scheduled", "promoted_live": false, "gate_reasons": ["rocket_or_grade"], "oi_funding_ls_shadow": {"oi_change_pct": 0.18909107072861414, "oi_combo": "down_up", "funding_rate": 0.004983, "ls_ratio": 2.44, "d_oi": 6, "d_funding": 0, "d_ls": 3, "total_delta": 9, "rocket_old": 54, "rocket_would_be": 63}, "bos_body_close_shadow": {"wick_only_type": null, "body_close_type": null, "disagree": false, "downgraded_to_invalid": false, "body_close_label": "структура не определена"}, "order_block_shadow": {"live": {"bull": false, "bull_zone": null, "bear": false, "bear_zone": null}, "methodology": {"bull": false, "bull_zone": null, "bear": false, "bear_zone": null}}}]}