{"schema_version": 1, "records": [{"ts": 1784291330.9472463, "symbol": "BONK", "direction": "short", "entry_lo": 3.805e-06, "entry_hi": 3.832e-06, "sl": 3.927e-06, "tp1": 3.561e-06, "tp2": 3.415e-06, "tp3": 3.195e-06, "rr_tp1_live": 2.0, "shadow_rr_gate_pass": true, "breaker_mitigation": null, "divergence": {"bearish_classical": false, "bearish_hidden": false, "bullish_classical": false, "bullish_hidden": false}, "bpr_zone_count": 6, "bpr_confluence": true, "whale_klvl_confluence": false, "whale_klvl_matches": [], "amd_phase_methodology": {"phase": "distribution_bear", "nymidnight_price": 3.34e-06, "price_vs_nymidnight": "below"}, "inducement": {"inducement_swept": false, "detail": null}, "order_block_live": {"bull": false, "bull_zone": null, "bear": false, "bear_zone": null}, "order_block_methodology": {"bull": false, "bull_zone": null, "bear": false, "bear_zone": null}, "chart_patterns": {"flag": {"bull": false, "bear": false, "target": null}, "head_shoulders": {"top": true, "bottom": false, "target": 3.1200000000000006e-06}, "triangle": {"type": null}}, "patches_affected": ["05-bpr"], "discrepancy": ["bpr: зона входа пересекается со свежим BPR (confluence)"], "live_journal_id": null, "tz13_shadow": {"ok": true, "block1_bias": {"bias": "SHORT", "structure_1d": "не определена", "tf_agreement": "4H EMA задаёт направление, 1D структура не подтверждает явно", "detail": ["1D структура: не определена", "4H EMA-стек: медвежий", "1H EMA-стек (контекст входа): недостаточно данных"], "key_low": null, "key_high": null}, "block2_elliott": {"elliott_1d": {"wave": "2", "label": "похоже на волну 2 (коррекция перед волной 3)", "note": "потенциальный вход у завершения коррекции", "score_delta": 5}, "elliott_4h": {"wave": "2", "label": "похоже на волну 2 (коррекция перед волной 3)", "note": "потенциальный вход у завершения коррекции", "score_delta": 5}}, "block3_setup_type": {"setup_type": "AMD", "label": "AMD — фаза distribution_bear (цена below NY-midnight)", "detail": {"phase": "distribution_bear", "nymidnight_price": 3.34e-06, "price_vs_nymidnight": "below"}}, "block4_zones": {"above": [{"lo": 3.80534160526449e-06, "hi": 3.83166160526449e-06, "mid": 3.81850160526449e-06, "touches": 1, "hours_ago": 0, "sources": ["ema"]}, {"lo": 3.89e-06, "hi": 3.95e-06, "mid": 3.9300000000000005e-06, "touches": 7, "hours_ago": 68, "sources": ["4h"]}, {"lo": 4.0080891420367515e-06, "hi": 4.034409142036751e-06, "mid": 4.021249142036751e-06, "touches": 1, "hours_ago": 0, "sources": ["ema"]}, {"lo": 4.01e-06, "hi": 4.07e-06, "mid": 4.041428571428572e-06, "touches": 7, "hours_ago": 116, "sources": ["4h"]}, {"lo": 4.14e-06, "hi": 4.1706599999999995e-06, "mid": 4.1575e-06, "touches": 4, "hours_ago": 140, "sources": ["4h"]}, {"lo": 4.220537522209406e-06, "hi": 4.246857522209406e-06, "mid": 4.233697522209406e-06, "touches": 1, "hours_ago": 0, "sources": ["ema"]}, {"lo": 4.31434e-06, "hi": 4.3406599999999995e-06, "mid": 4.3275e-06, "touches": 4, "hours_ago": 424, "sources": ["4h"]}, {"lo": 4.39e-06, "hi": 4.44e-06, "mid": 4.418e-06, "touches": 5, "hours_ago": 356, "sources": ["4h"]}, {"lo": 4.69684e-06, "hi": 4.72316e-06, "mid": 4.71e-06, "touches": 2, "hours_ago": 276, "sources": ["4h"]}], "below": []}, "block5_checklist": {"items": [["Тренд старшего ТФ (1D) совпадает с направлением", false], ["Свежий свип ликвидности в пользу направления", false], ["Цена у зоны интереса (не в вакууме)", false], ["Killzone активна или близко", true], ["Funding не против позиции", true], ["R:R по структуре ≥ 1:1.5", true]], "score": 3}, "block6_liquidity": {"sweep_1h": null, "sweep_4h": null, "equal_levels": [{"price": 4.04e-06, "kind": "high", "touches": 2}, {"price": 4.165e-06, "kind": "high", "touches": 2}, {"price": 4.32e-06, "kind": "high", "touches": 2}, {"price": 3.945e-06, "kind": "low", "touches": 4}, {"price": 4.035e-06, "kind": "low", "touches": 2}, {"price": 4.065e-06, "kind": "low", "touches": 2}]}, "block7_oi": {"oi_change_pct": 0.0, "oi_combo": null, "funding": null, "ls_ratio": 1.0}, "block8_killzone": {"active": {"name": "🇺🇸 NY Open", "start": 840, "end": 1020, "quality": "A", "desc": "Продолжение дневного диапазона, часто коррекция после Лондона", "remaining_min": 92}, "next": {"name": "🇬🇧 Лондон Close", "start": 1020, "end": 1140, "quality": "B", "desc": "Закрытие Лондона -- два источника, точная граница расходится (см. докстринг)", "in_min": 92}, "is_good": true, "hour": 15, "all_zones": [{"name": "🌏 Азиатская сессия", "start": 0, "end": 480, "quality": "B", "desc": "Низкая волатильность, часто рендж или хай/лоу дня"}, {"name": "🇬🇧 Лондон Open", "start": 540, "end": 720, "quality": "A+", "desc": "Наибольшие объёмы дня, ищем хай/лоу дня"}, {"name": "🇺🇸 NY Open", "start": 840, "end": 1020, "quality": "A", "desc": "Продолжение дневного диапазона, часто коррекция после Лондона", "remaining_min": 92}, {"name": "🇬🇧 Лондон Close", "start": 1020, "end": 1140, "quality": "B", "desc": "Закрытие Лондона -- два источника, точная граница расходится (см. докстринг)"}, {"name": "🇺🇸 NY Close", "start": 1380, "end": 1440, "quality": "C", "desc": "Закрытие Нью-Йорка, не подтверждено источником"}]}, "block9_phase": {"phase": "Маркдаун (Markdown)", "note": "объём: нет данных (источник свечей не отдаёт объём по этой монете)"}, "block10_dca": {"entry1": 3.80534160526449e-06, "entry2": 3.81850160526449e-06, "entry3": 3.83166160526449e-06, "weights": "50/30/20"}, "block11_tp_rr": {"tp1": 3.561118525001266e-06, "tp2": 3.4145846768433316e-06, "tp3": 3.1947839046064302e-06, "rr_tp1": 2.0, "rr_tp2": 3.2, "rr_tp3": 5.0, "rr_gate_pass": true}, "block12_sl": {"sl": 3.927453145396102e-06, "buffer_pct": 2.5}, "block13_verdict": {"has_setup": false, "direction": "short", "score": 3, "text": "шорт: сетапа нет (чеклист 3/6), тип сетапа: AMD — фаза distribution_bear (цена below NY-midnight)"}, "direction": "short", "score": 3, "entry_zone": {"lo": 3.80534160526449e-06, "hi": 3.83166160526449e-06}, "sl": 3.927453145396102e-06, "tp1": 3.561118525001266e-06, "tp2": 3.4145846768433316e-06, "tp3": 3.1947839046064302e-06, "setup_type": "AMD"}, "tz13_score": 3, "tz13_direction": "short", "tz13_setup_type": "AMD", "tz13_entry_zone": {"lo": 3.80534160526449e-06, "hi": 3.83166160526449e-06}, "tz13_sl": 3.927453145396102e-06, "tz13_tp1": 3.561118525001266e-06, "tz13_tp2": 3.4145846768433316e-06, "tz13_tp3": 3.1947839046064302e-06, "sweep_1h": null, "sweep_4h": null, "source": "send_scheduled", "promoted_live": false, "gate_reasons": ["rsi_extreme_short", "rocket_or_grade"], "oi_funding_ls_shadow": {"oi_change_pct": 0.0, "oi_combo": null, "funding_rate": -0.1843, "ls_ratio": 1.0, "d_oi": 0, "d_funding": -4, "d_ls": 0, "total_delta": -4, "rocket_old": 49, "rocket_would_be": 45}, "bos_body_close_shadow": {"wick_only_type": "BOS_bear", "body_close_type": "BOS_bear", "disagree": false, "downgraded_to_invalid": false, "body_close_label": "BOS — пробой структуры вниз по тренду, закрытие подтверждено (согласовано с bias SHORT)"}, "order_block_shadow": {"live": {"bull": false, "bull_zone": null, "bear": false, "bear_zone": null}, "methodology": {"bull": false, "bull_zone": null, "bear": false, "bear_zone": null}}}, {"ts": 1784291335.188291, "type": "ls_contrarian_shadow", "symbol": "DOT", "ls": 2.5211267605633805, "funding": 0.000166, "is_extreme": true, "trend_direction": "LONG", "contrarian_direction": "SHORT", "diverges": true, "live_direction": "LONG", "live_score_100": 29}, {"ts": 1784291351.9397054, "symbol": "JTO", "direction": "short", "entry_lo": 0.5787868, "entry_hi": 0.5832132, "sl": 0.59779353, "tp1": 0.54077334, "tp2": 0.51796526, "tp3": 0.48375315, "rr_tp1_live": 2.0, "shadow_rr_gate_pass": true, "breaker_mitigation": "mitigation", "divergence": {"bearish_classical": false, "bearish_hidden": false, "bullish_classical": false, "bullish_hidden": false}, "bpr_zone_count": 5, "bpr_confluence": false, "whale_klvl_confluence": false, "whale_klvl_matches": [], "amd_phase_methodology": {"phase": "distribution_bear", "nymidnight_price": 0.5616, "price_vs_nymidnight": "below"}, "inducement": {"inducement_swept": false, "detail": null}, "order_block_live": {"bull": false, "bull_zone": null, "bear": false, "bear_zone": null}, "order_block_methodology": {"bull": false, "bull_zone": null, "bear": false, "bear_zone": null}, "chart_patterns": {"flag": {"bull": false, "bear": true, "target": 0.43599999999999994}, "head_shoulders": {"top": true, "bottom": false, "target": 0.5740999999999998}, "triangle": {"type": null}}, "patches_affected": ["03-breaker-mitigation"], "discrepancy": [], "live_journal_id": null, "tz13_shadow": {"ok": true, "block1_bias": {"bias": "SHORT", "structure_1d": "LH/LL (даунтренд)", "tf_agreement": "1D и 4H согласованы", "detail": ["1D структура: LH/LL (даунтренд)", "4H EMA-стек: медвежий", "1H EMA-стек (контекст входа): недостаточно данных", "Ключевой минимум: 0.581 (пробой = предпосылка разворота/продолжения вниз)", "Ключевой хай: 0.6884 (снятие = цель движения вверх)"], "key_low": {"price": 0.581, "bars_ago": 5}, "key_high": {"price": 0.6884, "bars_ago": 4}}, "block2_elliott": {"elliott_1d": {"wave": null, "label": "волна не определена", "note": "структура неоднозначная", "score_delta": 0}, "elliott_4h": {"wave": null, "label": "волна не определена", "note": "структура неоднозначная", "score_delta": 0}}, "block3_setup_type": {"setup_type": "AMD", "label": "AMD — фаза distribution_bear (цена below NY-midnight)", "detail": {"phase": "distribution_bear", "nymidnight_price": 0.5616, "price_vs_nymidnight": "below"}}, "block4_zones": {"above": [{"lo": 0.5787867999999999, "hi": 0.5832132, "mid": 0.581, "touches": 2, "hours_ago": 120, "sources": ["1d", "4h"]}, {"lo": 0.5928467999999999, "hi": 0.5972732, "mid": 0.5950599999999999, "touches": 5, "hours_ago": 24, "sources": ["1d", "1h", "4h"]}, {"lo": 0.6047, "hi": 0.6132, "mid": 0.607475, "touches": 8, "hours_ago": 22, "sources": ["1d", "1h", "4h"]}, {"lo": 0.6223091567995185, "hi": 0.6267355567995185, "mid": 0.6245223567995185, "touches": 1, "hours_ago": 0, "sources": ["ema"]}, {"lo": 0.6223, "hi": 0.6273882, "mid": 0.6251749999999999, "touches": 4, "hours_ago": 31, "sources": ["1h", "4h"]}, {"lo": 0.6333, "hi": 0.6378798666666667, "mid": 0.6356666666666667, "touches": 6, "hours_ago": 42, "sources": ["1h", "4h"]}, {"lo": 0.65119256320443, "hi": 0.65561896320443, "mid": 0.65340576320443, "touches": 1, "hours_ago": 0, "sources": ["ema"]}, {"lo": 0.6571127179954818, "hi": 0.6615391179954818, "mid": 0.6593259179954818, "touches": 1, "hours_ago": 0, "sources": ["ema"]}, {"lo": 0.6607, "hi": 0.667, "mid": 0.66435, "touches": 4, "hours_ago": 76, "sources": ["4h"]}, {"lo": 0.6726367999999999, "hi": 0.6770632, "mid": 0.67485, "touches": 2, "hours_ago": 588, "sources": ["1d", "4h"]}, {"lo": 0.6860534666666667, "hi": 0.6904798666666667, "mid": 0.6882666666666667, "touches": 3, "hours_ago": 96, "sources": ["1d", "4h"]}, {"lo": 0.6959, "hi": 0.7148, "mid": 0.7052181818181819, "touches": 11, "hours_ago": 264, "sources": ["1d", "4h"]}, {"lo": 0.7260368, "hi": 0.7304632000000001, "mid": 0.7282500000000001, "touches": 2, "hours_ago": 348, "sources": ["4h"]}, {"lo": 0.7346868, "hi": 0.7391132, "mid": 0.7369, "touches": 2, "hours_ago": 276, "sources": ["4h"]}, {"lo": 0.7483, "hi": 0.7534465333333333, "mid": 0.7512333333333333, "touches": 3, "hours_ago": 248, "sources": ["4h"]}, {"lo": 0.7629868, "hi": 0.7674132, "mid": 0.7652, "touches": 2, "hours_ago": 372, "sources": ["4h"]}, {"lo": 0.7822201333333333, "hi": 0.7866465333333333, "mid": 0.7844333333333333, "touches": 3, "hours_ago": 336, "sources": ["4h"]}, {"lo": 0.7977868, "hi": 0.8022132000000001, "mid": 0.8, "touches": 2, "hours_ago": 240, "sources": ["1d", "4h"]}, {"lo": 0.8079, "hi": 0.82, "mid": 0.8132666666666667, "touches": 6, "hours_ago": 360, "sources": ["1d", "4h"]}, {"lo": 0.8773868, "hi": 0.8818132000000001, "mid": 0.8796, "touches": 2, "hours_ago": 744, "sources": ["1d", "4h"]}, {"lo": 0.8826868, "hi": 0.8871132, "mid": 0.8849, "touches": 2, "hours_ago": 500, "sources": ["1d", "4h"]}], "below": []}, "block5_checklist": {"items": [["Тренд старшего ТФ (1D) совпадает с направлением", true], ["Свежий свип ликвидности в пользу направления", false], ["Цена у зоны интереса (не в вакууме)", false], ["Killzone активна или близко", true], ["Funding не против позиции", true], ["R:R по структуре ≥ 1:1.5", true]], "score": 4}, "block6_liquidity": {"sweep_1h": {"type": "sweep_low", "level": 0.5858, "bars_ago": 16, "volume_confirmed": true}, "sweep_4h": null, "equal_levels": [{"price": 0.63615, "kind": "high", "touches": 2}, {"price": 0.7369, "kind": "high", "touches": 2}, {"price": 0.5951500000000001, "kind": "low", "touches": 2}, {"price": 0.60865, "kind": "low", "touches": 2}, {"price": 0.7011499999999999, "kind": "low", "touches": 2}, {"price": 0.70794, "kind": "low", "touches": 5}, {"price": 0.7526999999999999, "kind": "low", "touches": 2}]}, "block7_oi": {"oi_change_pct": 0.0, "oi_combo": null, "funding": null, "ls_ratio": 1.58}, "block8_killzone": {"active": {"name": "🇺🇸 NY Open", "start": 840, "end": 1020, "quality": "A", "desc": "Продолжение дневного диапазона, часто коррекция после Лондона", "remaining_min": 91}, "next": {"name": "🇬🇧 Лондон Close", "start": 1020, "end": 1140, "quality": "B", "desc": "Закрытие Лондона -- два источника, точная граница расходится (см. докстринг)", "in_min": 91}, "is_good": true, "hour": 15, "all_zones": [{"name": "🌏 Азиатская сессия", "start": 0, "end": 480, "quality": "B", "desc": "Низкая волатильность, часто рендж или хай/лоу дня"}, {"name": "🇬🇧 Лондон Open", "start": 540, "end": 720, "quality": "A+", "desc": "Наибольшие объёмы дня, ищем хай/лоу дня"}, {"name": "🇺🇸 NY Open", "start": 840, "end": 1020, "quality": "A", "desc": "Продолжение дневного диапазона, часто коррекция после Лондона", "remaining_min": 91}, {"name": "🇬🇧 Лондон Close", "start": 1020, "end": 1140, "quality": "B", "desc": "Закрытие Лондона -- два источника, точная граница расходится (см. докстринг)"}, {"name": "🇺🇸 NY Close", "start": 1380, "end": 1440, "quality": "C", "desc": "Закрытие Нью-Йорка, не подтверждено источником"}]}, "block9_phase": {"phase": "Маркдаун (Markdown)", "note": "объём: доступен, но не используется в этой упрощённой эвристике"}, "block10_dca": {"entry1": 0.5787867999999999, "entry2": 0.581, "entry3": 0.5832132, "weights": "50/30/20"}, "block11_tp_rr": {"tp1": 0.54077334, "tp2": 0.517965264, "tp3": 0.4837531500000001, "rr_tp1": 2.0, "rr_tp2": 3.2, "rr_tp3": 5.0, "rr_gate_pass": true}, "block12_sl": {"sl": 0.5977935299999999, "buffer_pct": 2.5}, "block13_verdict": {"has_setup": true, "direction": "short", "score": 4, "text": "шорт: сетап готов (чеклист 4/6), тип сетапа: AMD — фаза distribution_bear (цена below NY-midnight)"}, "direction": "short", "score": 4, "entry_zone": {"lo": 0.5787867999999999, "hi": 0.5832132}, "sl": 0.5977935299999999, "tp1": 0.54077334, "tp2": 0.517965264, "tp3": 0.4837531500000001, "setup_type": "AMD"}, "tz13_score": 4, "tz13_direction": "short", "tz13_setup_type": "AMD", "tz13_entry_zone": {"lo": 0.5787867999999999, "hi": 0.5832132}, "tz13_sl": 0.5977935299999999, "tz13_tp1": 0.54077334, "tz13_tp2": 0.517965264, "tz13_tp3": 0.4837531500000001, "sweep_1h": {"type": "sweep_low", "level": 0.5858, "bars_ago": 16, "volume_confirmed": true}, "sweep_4h": null, "source": "send_scheduled", "promoted_live": false, "gate_reasons": ["rocket_or_grade"], "oi_funding_ls_shadow": {"oi_change_pct": 0.0, "oi_combo": null, "funding_rate": -0.004776, "ls_ratio": 1.58, "d_oi": 0, "d_funding": 0, "d_ls": 3, "total_delta": 3, "rocket_old": 49, "rocket_would_be": 52}, "bos_body_close_shadow": {"wick_only_type": "BOS_bear", "body_close_type": "BOS_bear", "disagree": false, "downgraded_to_invalid": false, "body_close_label": "BOS — пробой структуры вниз по тренду, закрытие подтверждено (согласовано с bias SHORT)"}, "order_block_shadow": {"live": {"bull": false, "bull_zone": null, "bear": false, "bear_zone": null}, "methodology": {"bull": false, "bull_zone": null, "bear": false, "bear_zone": null}}}, {"ts": 1784291355.884213, "symbol": "ZRO", "direction": "short", "entry_lo": 0.7868, "entry_hi": 0.8221, "sl": 0.8426525, "tp1": 0.7632, "tp2": 0.7316, "tp3": 0.5075375, "rr_tp1_live": 0.42, "shadow_rr_gate_pass": false, "breaker_mitigation": "mitigation", "divergence": {"bearish_classical": false, "bearish_hidden": false, "bullish_classical": false, "bullish_hidden": false}, "bpr_zone_count": 1, "bpr_confluence": false, "whale_klvl_confluence": false, "whale_klvl_matches": [], "amd_phase_methodology": {"phase": "distribution_bear", "nymidnight_price": 0.7982, "price_vs_nymidnight": "below"}, "inducement": {"inducement_swept": true, "detail": {"type": "sweep_low", "level": 0.8026, "bars_ago": 4, "volume_confirmed": false}}, "order_block_live": {"bull": false, "bull_zone": null, "bear": false, "bear_zone": null}, "order_block_methodology": {"bull": false, "bull_zone": null, "bear": false, "bear_zone": null}, "chart_patterns": {"flag": {"bull": false, "bear": false, "target": null}, "head_shoulders": {"top": true, "bottom": false, "target": 0.7836999999999998}, "triangle": {"type": null}}, "patches_affected": ["02-rr-gate", "03-breaker-mitigation"], "discrepancy": ["rr_gate: R:R 0.42 прошёл live-гейт (1.5), но НЕ прошёл бы shadow-гейт (2.0)"], "live_journal_id": null, "tz13_shadow": {"ok": true, "block1_bias": {"bias": "SHORT", "structure_1d": "смешанная (микс HH/LL)", "tf_agreement": "4H EMA задаёт направление, 1D структура не подтверждает явно", "detail": ["1D структура: смешанная (микс HH/LL)", "4H EMA-стек: медвежий", "1H EMA-стек (контекст входа): недостаточно данных", "Ключевой минимум: 0.8865 (пробой = предпосылка разворота/продолжения вниз)", "Ключевой хай: 0.9622 (снятие = цель движения вверх)"], "key_low": {"price": 0.8865, "bars_ago": 8}, "key_high": {"price": 0.9622, "bars_ago": 6}}, "block2_elliott": {"elliott_1d": {"wave": null, "label": "волна не определена", "note": "структура неоднозначная", "score_delta": 0}, "elliott_4h": {"wave": null, "label": "волна не определена", "note": "структура неоднозначная", "score_delta": 0}}, "block3_setup_type": {"setup_type": "SH-BOS-RTO", "label": "SH-BOS-RTO — свип sweep_low (4 баров назад) + BOS — пробой структуры вниз по тренду, закрытие подтверждено (согласовано с bias SHORT)", "detail": {"sweep": {"type": "sweep_low", "level": 0.8026, "bars_ago": 4, "volume_confirmed": false}, "bos": {"type": "BOS_bear", "label": "BOS — пробой структуры вниз по тренду, закрытие подтверждено (согласовано с bias SHORT)", "aligned": true}}}, "block4_zones": {"above": [{"lo": 0.7868, "hi": 0.8221, "mid": 0.8077142857142857, "touches": 21, "hours_ago": 4, "sources": ["1d", "1h", "4h"]}, {"lo": 0.8303, "hi": 0.8468, "mid": 0.8374625000000001, "touches": 8, "hours_ago": 31, "sources": ["1h", "4h"]}, {"lo": 0.8524949949352711, "hi": 0.8587373949352712, "mid": 0.8556161949352712, "touches": 1, "hours_ago": 0, "sources": ["ema"]}, {"lo": 0.8715439366226406, "hi": 0.8777863366226407, "mid": 0.8746651366226407, "touches": 1, "hours_ago": 0, "sources": ["ema"]}, {"lo": 0.8877541452743551, "hi": 0.8939965452743552, "mid": 0.8908753452743552, "touches": 1, "hours_ago": 0, "sources": ["ema"]}, {"lo": 0.8788, "hi": 0.9099, "mid": 0.8921833333333333, "touches": 18, "hours_ago": 47, "sources": ["1d", "1h", "4h"]}, {"lo": 0.9286, "hi": 0.9373, "mid": 0.932, "touches": 5, "hours_ago": 172, "sources": ["4h"]}, {"lo": 0.9427121333333333, "hi": 0.9489545333333333, "mid": 0.9458333333333333, "touches": 3, "hours_ago": 192, "sources": ["4h"]}, {"lo": 0.9558, "hi": 0.9634462000000001, "mid": 0.9603250000000001, "touches": 4, "hours_ago": 144, "sources": ["1d", "4h"]}, {"lo": 0.9868, "hi": 0.9934462000000001, "mid": 0.990325, "touches": 4, "hours_ago": 216, "sources": ["4h"]}, {"lo": 1.0033788, "hi": 1.0096212, "mid": 1.0065, "touches": 2, "hours_ago": 600, "sources": ["1d", "4h"]}, {"lo": 1.0597788, "hi": 1.0660212, "mid": 1.0629, "touches": 2, "hours_ago": 256, "sources": ["1d", "4h"]}, {"lo": 1.2170788, "hi": 1.2233212, "mid": 1.2202, "touches": 3, "hours_ago": 744, "sources": ["1d", "4h"]}], "below": [{"lo": 0.7600787999999999, "hi": 0.7663212, "mid": 0.7632, "touches": 3, "hours_ago": 476, "sources": ["4h"]}, {"lo": 0.7284788, "hi": 0.7347212000000001, "mid": 0.7316, "touches": 2, "hours_ago": 448, "sources": ["1d", "4h"]}]}, "block5_checklist": {"items": [["Тренд старшего ТФ (1D) совпадает с направлением", false], ["Свежий свип ликвидности в пользу направления", false], ["Цена у зоны интереса (не в вакууме)", false], ["Killzone активна или близко", true], ["Funding не против позиции", true], ["R:R по структуре ≥ 1:1.5", false]], "score": 2}, "block6_liquidity": {"sweep_1h": {"type": "sweep_high", "level": 0.8183, "bars_ago": 11, "volume_confirmed": false}, "sweep_4h": {"type": "sweep_low", "level": 0.8026, "bars_ago": 4, "volume_confirmed": false}, "equal_levels": [{"price": 0.82145, "kind": "high", "touches": 2}, {"price": 0.8871333333333333, "kind": "high", "touches": 3}, {"price": 0.9458333333333333, "kind": "high", "touches": 3}, {"price": 0.96165, "kind": "high", "touches": 2}, {"price": 0.98775, "kind": "high", "touches": 2}, {"price": 0.7645, "kind": "low", "touches": 2}, {"price": 0.8376333333333333, "kind": "low", "touches": 3}, {"price": 0.8905, "kind": "low", "touches": 3}, {"price": 0.90005, "kind": "low", "touches": 2}, {"price": 0.9309, "kind": "low", "touches": 3}]}, "block7_oi": {"oi_change_pct": 0.0, "oi_combo": null, "funding": null, "ls_ratio": 1.83}, "block8_killzone": {"active": {"name": "🇺🇸 NY Open", "start": 840, "end": 1020, "quality": "A", "desc": "Продолжение дневного диапазона, часто коррекция после Лондона", "remaining_min": 91}, "next": {"name": "🇬🇧 Лондон Close", "start": 1020, "end": 1140, "quality": "B", "desc": "Закрытие Лондона -- два источника, точная граница расходится (см. докстринг)", "in_min": 91}, "is_good": true, "hour": 15, "all_zones": [{"name": "🌏 Азиатская сессия", "start": 0, "end": 480, "quality": "B", "desc": "Низкая волатильность, часто рендж или хай/лоу дня"}, {"name": "🇬🇧 Лондон Open", "start": 540, "end": 720, "quality": "A+", "desc": "Наибольшие объёмы дня, ищем хай/лоу дня"}, {"name": "🇺🇸 NY Open", "start": 840, "end": 1020, "quality": "A", "desc": "Продолжение дневного диапазона, часто коррекция после Лондона", "remaining_min": 91}, {"name": "🇬🇧 Лондон Close", "start": 1020, "end": 1140, "quality": "B", "desc": "Закрытие Лондона -- два источника, точная граница расходится (см. докстринг)"}, {"name": "🇺🇸 NY Close", "start": 1380, "end": 1440, "quality": "C", "desc": "Закрытие Нью-Йорка, не подтверждено источником"}]}, "block9_phase": {"phase": "Маркдаун (Markdown)", "note": "объём: доступен, но не используется в этой упрощённой эвристике"}, "block10_dca": {"entry1": 0.7868, "entry2": 0.8044500000000001, "entry3": 0.8221, "weights": "50/30/20"}, "block11_tp_rr": {"tp1": 0.7632, "tp2": 0.7316, "tp3": 0.5075375000000002, "rr_tp1": 0.42, "rr_tp2": 0.99, "rr_tp3": 5.0, "rr_gate_pass": false}, "block12_sl": {"sl": 0.8426525, "buffer_pct": 2.5}, "block13_verdict": {"has_setup": false, "direction": "short", "score": 2, "text": "шорт: сетапа нет (чеклист 2/6), тип сетапа: SH-BOS-RTO — свип sweep_low (4 баров назад) + BOS — пробой структуры вниз по тренду, закрытие подтверждено (согласовано с bias SHORT)"}, "direction": "short", "score": 2, "entry_zone": {"lo": 0.7868, "hi": 0.8221}, "sl": 0.8426525, "tp1": 0.7632, "tp2": 0.7316, "tp3": 0.5075375000000002, "setup_type": "SH-BOS-RTO"}, "tz13_score": 2, "tz13_direction": "short", "tz13_setup_type": "SH-BOS-RTO", "tz13_entry_zone": {"lo": 0.7868, "hi": 0.8221}, "tz13_sl": 0.8426525, "tz13_tp1": 0.7632, "tz13_tp2": 0.7316, "tz13_tp3": 0.5075375000000002, "sweep_1h": {"type": "sweep_high", "level": 0.8183, "bars_ago": 11, "volume_confirmed": false}, "sweep_4h": {"type": "sweep_low", "level": 0.8026, "bars_ago": 4, "volume_confirmed": false}, "source": "send_scheduled", "promoted_live": false, "gate_reasons": ["rsi_extreme_short", "rocket_or_grade", "rr_gate"], "oi_funding_ls_shadow": {"oi_change_pct": 0.0, "oi_combo": null, "funding_rate": 0.005, "ls_ratio": 1.83, "d_oi": 0, "d_funding": 0, "d_ls": 3, "total_delta": 3, "rocket_old": 51, "rocket_would_be": 54}, "bos_body_close_shadow": {"wick_only_type": "BOS_bear", "body_close_type": "BOS_bear", "disagree": false, "downgraded_to_invalid": false, "body_close_label": "BOS — пробой структуры вниз по тренду, закрытие подтверждено (согласовано с bias SHORT)"}, "order_block_shadow": {"live": {"bull": false, "bull_zone": null, "bear": false, "bear_zone": null}, "methodology": {"bull": false, "bull_zone": null, "bear": false, "bear_zone": null}}}, {"ts": 1784291359.6715262, "symbol": "GRASS", "direction": "short", "entry_lo": 0.3725448, "entry_hi": 0.37637, "sl": 0.38577925, "tp1": 0.361595, "tp2": 0.35076, "tp3": 0.33422, "rr_tp1_live": 0.83, "shadow_rr_gate_pass": false, "breaker_mitigation": "mitigation", "divergence": {"bearish_classical": false, "bearish_hidden": false, "bullish_classical": false, "bullish_hidden": false}, "bpr_zone_count": 6, "bpr_confluence": false, "whale_klvl_confluence": false, "whale_klvl_matches": [], "amd_phase_methodology": {"phase": "distribution_bear", "nymidnight_price": 0.3658, "price_vs_nymidnight": "below"}, "inducement": {"inducement_swept": true, "detail": {"type": "sweep_low", "level": 0.37268, "bars_ago": 3, "volume_confirmed": false}}, "order_block_live": {"bull": false, "bull_zone": null, "bear": false, "bear_zone": null}, "order_block_methodology": {"bull": true, "bull_zone": [0.3633, 0.3739], "bear": false, "bear_zone": null}, "chart_patterns": {"flag": {"bull": false, "bear": true, "target": 0.18751999999999996}, "head_shoulders": {"top": true, "bottom": false, "target": 0.32504999999999995}, "triangle": {"type": null}}, "patches_affected": ["02-rr-gate", "03-breaker-mitigation", "07-order-block-body"], "discrepancy": ["rr_gate: R:R 0.83 прошёл live-гейт (1.5), но НЕ прошёл бы shadow-гейт (2.0)", "order_block: live(bull=False,bear=False) vs methodology-тело(bull=True,bear=False)"], "live_journal_id": null, "tz13_shadow": {"ok": true, "block1_bias": {"bias": "SHORT", "structure_1d": "смешанная (микс HH/LL)", "tf_agreement": "4H EMA задаёт направление, 1D структура не подтверждает явно", "detail": ["1D структура: смешанная (микс HH/LL)", "4H EMA-стек: медвежий", "1H EMA-стек (контекст входа): недостаточно данных", "Ключевой минимум: 0.35076 (пробой = предпосылка разворота/продолжения вниз)", "Ключевой хай: 0.4244 (снятие = цель движения вверх)"], "key_low": {"price": 0.35076, "bars_ago": 3}, "key_high": {"price": 0.4244, "bars_ago": 6}}, "block2_elliott": {"elliott_1d": {"wave": null, "label": "волна не определена", "note": "структура неоднозначная", "score_delta": 0}, "elliott_4h": {"wave": null, "label": "волна не определена", "note": "структура неоднозначная", "score_delta": 0}}, "block3_setup_type": {"setup_type": "SH-BOS-RTO", "label": "SH-BOS-RTO — свип sweep_low (3 баров назад) + BOS — пробой структуры вниз по тренду, закрытие подтверждено (согласовано с bias SHORT)", "detail": {"sweep": {"type": "sweep_low", "level": 0.37268, "bars_ago": 3, "volume_confirmed": false}, "bos": {"type": "BOS_bear", "label": "BOS — пробой структуры вниз по тренду, закрытие подтверждено (согласовано с bias SHORT)", "aligned": true}}}, "block4_zones": {"above": [{"lo": 0.37254480000000006, "hi": 0.37637, "mid": 0.37400400000000006, "touches": 5, "hours_ago": 2, "sources": ["1h", "4h"]}, {"lo": 0.3808208, "hi": 0.3837392, "mid": 0.38228, "touches": 3, "hours_ago": 28, "sources": ["1h", "4h"]}, {"lo": 0.38484080000000004, "hi": 0.3877592, "mid": 0.38630000000000003, "touches": 3, "hours_ago": 136, "sources": ["1d", "4h"]}, {"lo": 0.39129080000000005, "hi": 0.39420920000000004, "mid": 0.39275000000000004, "touches": 2, "hours_ago": 39, "sources": ["1h", "4h"]}, {"lo": 0.3918270527589565, "hi": 0.3947454527589565, "mid": 0.3932862527589565, "touches": 1, "hours_ago": 0, "sources": ["ema"]}, {"lo": 0.39673, "hi": 0.40082, "mid": 0.39848124999999995, "touches": 8, "hours_ago": 25, "sources": ["1d", "1h", "4h"]}, {"lo": 0.404, "hi": 0.40961, "mid": 0.40694250000000004, "touches": 4, "hours_ago": 120, "sources": ["4h"]}, {"lo": 0.4135315509447388, "hi": 0.4164499509447388, "mid": 0.4149907509447388, "touches": 1, "hours_ago": 0, "sources": ["ema"]}, {"lo": 0.4236011084136459, "hi": 0.4265195084136459, "mid": 0.4250603084136459, "touches": 1, "hours_ago": 0, "sources": ["ema"]}, {"lo": 0.4244, "hi": 0.42977, "mid": 0.427022, "touches": 5, "hours_ago": 144, "sources": ["1d", "4h"]}, {"lo": 0.4455141333333334, "hi": 0.4484325333333334, "mid": 0.4469733333333334, "touches": 3, "hours_ago": 404, "sources": ["1d", "4h"]}, {"lo": 0.4564258, "hi": 0.4593442, "mid": 0.457885, "touches": 2, "hours_ago": 372, "sources": ["4h"]}, {"lo": 0.46921, "hi": 0.47319, "mid": 0.4709525, "touches": 4, "hours_ago": 264, "sources": ["4h"]}, {"lo": 0.48152079999999997, "hi": 0.48443919999999996, "mid": 0.48297999999999996, "touches": 2, "hours_ago": 412, "sources": ["4h"]}, {"lo": 0.49611413333333326, "hi": 0.49903253333333325, "mid": 0.49757333333333326, "touches": 3, "hours_ago": 340, "sources": ["4h"]}, {"lo": 0.5114107999999999, "hi": 0.5143291999999999, "mid": 0.5128699999999999, "touches": 3, "hours_ago": 460, "sources": ["1d", "4h"]}, {"lo": 0.5182658, "hi": 0.5211842, "mid": 0.519725, "touches": 2, "hours_ago": 380, "sources": ["4h"]}, {"lo": 0.5319008, "hi": 0.5348191999999999, "mid": 0.53336, "touches": 3, "hours_ago": 480, "sources": ["1d", "4h"]}, {"lo": 0.5457158, "hi": 0.5486342, "mid": 0.547175, "touches": 2, "hours_ago": 292, "sources": ["4h"]}, {"lo": 0.5981808, "hi": 0.6010992, "mid": 0.59964, "touches": 2, "hours_ago": 336, "sources": ["1d", "4h"]}], "below": [{"lo": 0.3601358, "hi": 0.3630542, "mid": 0.361595, "touches": 4, "hours_ago": 4, "sources": ["1h", "4h"]}, {"lo": 0.3493008, "hi": 0.3522192, "mid": 0.35076, "touches": 2, "hours_ago": 72, "sources": ["1d", "4h"]}, {"lo": 0.3327608, "hi": 0.3356792, "mid": 0.33422, "touches": 2, "hours_ago": 216, "sources": ["1d", "4h"]}]}, "block5_checklist": {"items": [["Тренд старшего ТФ (1D) совпадает с направлением", false], ["Свежий свип ликвидности в пользу направления", false], ["Цена у зоны интереса (не в вакууме)", false], ["Killzone активна или близко", true], ["Funding не против позиции", true], ["R:R по структуре ≥ 1:1.5", false]], "score": 2}, "block6_liquidity": {"sweep_1h": {"type": "sweep_low", "level": 0.37365, "bars_ago": 15, "volume_confirmed": false}, "sweep_4h": {"type": "sweep_low", "level": 0.37268, "bars_ago": 3, "volume_confirmed": false}, "equal_levels": [{"price": 0.39898000000000006, "kind": "high", "touches": 3}, {"price": 0.42961499999999997, "kind": "high", "touches": 2}, {"price": 0.469665, "kind": "high", "touches": 2}, {"price": 0.497855, "kind": "high", "touches": 2}, {"price": 0.5129699999999999, "kind": "high", "touches": 2}, {"price": 0.547175, "kind": "high", "touches": 2}, {"price": 0.36166, "kind": "low", "touches": 2}, {"price": 0.457885, "kind": "low", "touches": 2}]}, "block7_oi": {"oi_change_pct": 0.0, "oi_combo": null, "funding": null, "ls_ratio": 1.81}, "block8_killzone": {"active": {"name": "🇺🇸 NY Open", "start": 840, "end": 1020, "quality": "A", "desc": "Продолжение дневного диапазона, часто коррекция после Лондона", "remaining_min": 91}, "next": {"name": "🇬🇧 Лондон Close", "start": 1020, "end": 1140, "quality": "B", "desc": "Закрытие Лондона -- два источника, точная граница расходится (см. докстринг)", "in_min": 91}, "is_good": true, "hour": 15, "all_zones": [{"name": "🌏 Азиатская сессия", "start": 0, "end": 480, "quality": "B", "desc": "Низкая волатильность, часто рендж или хай/лоу дня"}, {"name": "🇬🇧 Лондон Open", "start": 540, "end": 720, "quality": "A+", "desc": "Наибольшие объёмы дня, ищем хай/лоу дня"}, {"name": "🇺🇸 NY Open", "start": 840, "end": 1020, "quality": "A", "desc": "Продолжение дневного диапазона, часто коррекция после Лондона", "remaining_min": 91}, {"name": "🇬🇧 Лондон Close", "start": 1020, "end": 1140, "quality": "B", "desc": "Закрытие Лондона -- два источника, точная граница расходится (см. докстринг)"}, {"name": "🇺🇸 NY Close", "start": 1380, "end": 1440, "quality": "C", "desc": "Закрытие Нью-Йорка, не подтверждено источником"}]}, "block9_phase": {"phase": "Маркдаун (Markdown)", "note": "объём: доступен, но не используется в этой упрощённой эвристике"}, "block10_dca": {"entry1": 0.37254480000000006, "entry2": 0.37445740000000005, "entry3": 0.37637, "weights": "50/30/20"}, "block11_tp_rr": {"tp1": 0.361595, "tp2": 0.35076, "tp3": 0.33422, "rr_tp1": 0.83, "rr_tp2": 1.65, "rr_tp3": 2.9, "rr_gate_pass": false}, "block12_sl": {"sl": 0.38577924999999996, "buffer_pct": 2.5}, "block13_verdict": {"has_setup": false, "direction": "short", "score": 2, "text": "шорт: сетапа нет (чеклист 2/6), тип сетапа: SH-BOS-RTO — свип sweep_low (3 баров назад) + BOS — пробой структуры вниз по тренду, закрытие подтверждено (согласовано с bias SHORT)"}, "direction": "short", "score": 2, "entry_zone": {"lo": 0.37254480000000006, "hi": 0.37637}, "sl": 0.38577924999999996, "tp1": 0.361595, "tp2": 0.35076, "tp3": 0.33422, "setup_type": "SH-BOS-RTO"}, "tz13_score": 2, "tz13_direction": "short", "tz13_setup_type": "SH-BOS-RTO", "tz13_entry_zone": {"lo": 0.37254480000000006, "hi": 0.37637}, "tz13_sl": 0.38577924999999996, "tz13_tp1": 0.361595, "tz13_tp2": 0.35076, "tz13_tp3": 0.33422, "sweep_1h": {"type": "sweep_low", "level": 0.37365, "bars_ago": 15, "volume_confirmed": false}, "sweep_4h": {"type": "sweep_low", "level": 0.37268, "bars_ago": 3, "volume_confirmed": false}, "source": "send_scheduled", "promoted_live": false, "gate_reasons": ["rocket_or_grade", "rr_gate"], "oi_funding_ls_shadow": {"oi_change_pct": 0.0, "oi_combo": null, "funding_rate": 0.005, "ls_ratio": 1.81, "d_oi": 0, "d_funding": 0, "d_ls": 3, "total_delta": 3, "rocket_old": 41, "rocket_would_be": 44}, "bos_body_close_shadow": {"wick_only_type": "BOS_bear", "body_close_type": "BOS_bear", "disagree": false, "downgraded_to_invalid": false, "body_close_label": "BOS — пробой структуры вниз по тренду, закрытие подтверждено (согласовано с bias SHORT)"}, "order_block_shadow": {"live": {"bull": false, "bull_zone": null, "bear": false, "bear_zone": null}, "methodology": {"bull": true, "bull_zone": [0.3633, 0.3739], "bear": false, "bear_zone": null}}}, {"ts": 1784291362.9306, "symbol": "RIF", "direction": "short", "entry_lo": 0.130342, "entry_hi": 0.130342, "sl": 0.13425226, "tp1": 0.12773516, "tp2": 0.12612413, "tp3": 0.12351729, "rr_tp1_live": 0.67, "shadow_rr_gate_pass": false, "breaker_mitigation": null, "divergence": {}, "bpr_zone_count": 0, "bpr_confluence": false, "whale_klvl_confluence": false, "whale_klvl_matches": [], "amd_phase_methodology": {"phase": "distribution", "nymidnight_price": null, "price_vs_nymidnight": null}, "inducement": {"inducement_swept": false, "detail": null}, "order_block_live": {"bull": false, "bull_zone": null, "bear": false, "bear_zone": null}, "order_block_methodology": {"bull": false, "bull_zone": null, "bear": false, "bear_zone": null}, "chart_patterns": {"flag": {"bull": false, "bear": false, "target": null}, "head_shoulders": {"top": false, "bottom": false, "target": null}, "triangle": {"type": null}}, "patches_affected": ["02-rr-gate"], "discrepancy": ["rr_gate: R:R 0.67 прошёл live-гейт (1.5), но НЕ прошёл бы shadow-гейт (2.0)"], "live_journal_id": null, "tz13_shadow": {"ok": false, "error": "нет 4h-свечей"}, "tz13_score": null, "tz13_direction": null, "tz13_setup_type": null, "tz13_entry_zone": null, "tz13_sl": null, "tz13_tp1": null, "tz13_tp2": null, "tz13_tp3": null, "sweep_1h": null, "sweep_4h": null, "source": "send_scheduled", "promoted_live": false, "gate_reasons": ["rocket_or_grade", "rr_gate"], "oi_funding_ls_shadow": {"oi_change_pct": 0.0, "oi_combo": null, "funding_rate": 0.004173, "ls_ratio": 1.0, "d_oi": 0, "d_funding": 0, "d_ls": 0, "total_delta": 0, "rocket_old": 33, "rocket_would_be": 33}, "bos_body_close_shadow": {"wick_only_type": null, "body_close_type": null, "disagree": false, "downgraded_to_invalid": false, "body_close_label": "н/д -- нет 4h-свечей"}, "order_block_shadow": {"error": "нет 4h-свечей"}}, {"ts": 1784291366.0811834, "symbol": "DRV", "direction": "short", "entry_lo": 0.127762, "entry_hi": 0.127762, "sl": 0.13159486, "tp1": 0.12520676, "tp2": 0.12362762, "tp3": 0.12107238, "rr_tp1_live": 0.67, "shadow_rr_gate_pass": false, "breaker_mitigation": null, "divergence": {}, "bpr_zone_count": 0, "bpr_confluence": false, "whale_klvl_confluence": false, "whale_klvl_matches": [], "amd_phase_methodology": {"phase": "distribution", "nymidnight_price": null, "price_vs_nymidnight": null}, "inducement": {"inducement_swept": false, "detail": null}, "order_block_live": {"bull": false, "bull_zone": null, "bear": false, "bear_zone": null}, "order_block_methodology": {"bull": false, "bull_zone": null, "bear": false, "bear_zone": null}, "chart_patterns": {"flag": {"bull": false, "bear": false, "target": null}, "head_shoulders": {"top": false, "bottom": false, "target": null}, "triangle": {"type": null}}, "patches_affected": ["02-rr-gate"], "discrepancy": ["rr_gate: R:R 0.67 прошёл live-гейт (1.5), но НЕ прошёл бы shadow-гейт (2.0)"], "live_journal_id": null, "tz13_shadow": {"ok": false, "error": "нет 4h-свечей"}, "tz13_score": null, "tz13_direction": null, "tz13_setup_type": null, "tz13_entry_zone": null, "tz13_sl": null, "tz13_tp1": null, "tz13_tp2": null, "tz13_tp3": null, "sweep_1h": null, "sweep_4h": null, "source": "send_scheduled", "promoted_live": false, "gate_reasons": ["rocket_or_grade", "rr_gate"], "oi_funding_ls_shadow": {"oi_change_pct": 0.0, "oi_combo": null, "funding_rate": 0.009899999999999999, "ls_ratio": 1.0, "d_oi": 0, "d_funding": 0, "d_ls": 0, "total_delta": 0, "rocket_old": 30, "rocket_would_be": 30}, "bos_body_close_shadow": {"wick_only_type": null, "body_close_type": null, "disagree": false, "downgraded_to_invalid": false, "body_close_label": "н/д -- нет 4h-свечей"}, "order_block_shadow": {"error": "нет 4h-свечей"}}, {"ts": 1784291369.9040554, "symbol": "BTW", "direction": "short", "entry_lo": 0.05824, "entry_hi": 0.05951, "sl": 0.06099775, "tp1": 0.05757571, "tp2": 0.05654333, "tp3": 0.05282667, "rr_tp1_live": 0.24, "shadow_rr_gate_pass": false, "breaker_mitigation": "mitigation", "divergence": {"bearish_classical": false, "bearish_hidden": false, "bullish_classical": false, "bullish_hidden": true}, "bpr_zone_count": 8, "bpr_confluence": true, "whale_klvl_confluence": false, "whale_klvl_matches": [], "amd_phase_methodology": {"phase": "distribution_bear", "nymidnight_price": 0.05891, "price_vs_nymidnight": "below"}, "inducement": {"inducement_swept": true, "detail": {"type": "sweep_high", "level": 0.06122, "bars_ago": 3, "volume_confirmed": false}}, "order_block_live": {"bull": false, "bull_zone": null, "bear": false, "bear_zone": null}, "order_block_methodology": {"bull": false, "bull_zone": null, "bear": false, "bear_zone": null}, "chart_patterns": {"flag": {"bull": true, "bear": false, "target": 0.22347000000000003}, "head_shoulders": {"top": true, "bottom": false, "target": 0.0489}, "triangle": {"type": null}}, "patches_affected": ["02-rr-gate", "03-breaker-mitigation", "05-bpr"], "discrepancy": ["rr_gate: R:R 0.24 прошёл live-гейт (1.5), но НЕ прошёл бы shadow-гейт (2.0)", "bpr: зона входа пересекается со свежим BPR (confluence)"], "live_journal_id": null, "tz13_shadow": {"ok": true, "block1_bias": {"bias": "SHORT", "structure_1d": "LH/LL (даунтренд)", "tf_agreement": "1D и 4H согласованы", "detail": ["1D структура: LH/LL (даунтренд)", "4H EMA-стек: медвежий", "1H EMA-стек (контекст входа): недостаточно данных", "Ключевой минимум: 0.05291 (пробой = предпосылка разворота/продолжения вниз)", "Ключевой хай: 0.06439 (снятие = цель движения вверх)"], "key_low": {"price": 0.05291, "bars_ago": 2}, "key_high": {"price": 0.06439, "bars_ago": 2}}, "block2_elliott": {"elliott_1d": {"wave": null, "label": "волна не определена", "note": "структура неоднозначная", "score_delta": 0}, "elliott_4h": {"wave": null, "label": "волна не определена", "note": "структура неоднозначная", "score_delta": 0}}, "block3_setup_type": {"setup_type": "AMD", "label": "AMD — фаза distribution_bear (цена below NY-midnight)", "detail": {"phase": "distribution_bear", "nymidnight_price": 0.05891, "price_vs_nymidnight": "below"}}, "block4_zones": {"above": [{"lo": 0.05824, "hi": 0.05951, "mid": 0.05886888888888889, "touches": 9, "hours_ago": 12, "sources": ["1h", "4h"]}, {"lo": 0.06056023069685212, "hi": 0.061023270696852115, "mid": 0.060791750696852116, "touches": 1, "hours_ago": 0, "sources": ["ema"]}, {"lo": 0.06076, "hi": 0.06151, "mid": 0.06119727272727273, "touches": 11, "hours_ago": 9, "sources": ["1h", "4h"]}, {"lo": 0.06381242450501984, "hi": 0.06427546450501984, "mid": 0.06404394450501984, "touches": 1, "hours_ago": 0, "sources": ["ema"]}, {"lo": 0.06415848, "hi": 0.06462152, "mid": 0.06439, "touches": 2, "hours_ago": 48, "sources": ["1d", "4h"]}, {"lo": 0.06703347999999999, "hi": 0.06749651999999999, "mid": 0.06726499999999999, "touches": 2, "hours_ago": 176, "sources": ["4h"]}, {"lo": 0.06891848, "hi": 0.06938152, "mid": 0.06915, "touches": 2, "hours_ago": 208, "sources": ["4h"]}, {"lo": 0.0700700608494076, "hi": 0.0705331008494076, "mid": 0.0703015808494076, "touches": 1, "hours_ago": 0, "sources": ["ema"]}, {"lo": 0.07558181333333333, "hi": 0.07604485333333333, "mid": 0.07581333333333333, "touches": 3, "hours_ago": 464, "sources": ["1d", "4h"]}, {"lo": 0.08087847999999999, "hi": 0.08134151999999999, "mid": 0.08110999999999999, "touches": 2, "hours_ago": 500, "sources": ["4h"]}, {"lo": 0.08537848, "hi": 0.08584152, "mid": 0.08561, "touches": 2, "hours_ago": 288, "sources": ["1d", "4h"]}, {"lo": 0.20753848, "hi": 0.20800152000000002, "mid": 0.20777, "touches": 2, "hours_ago": 644, "sources": ["1d", "4h"]}], "below": [{"lo": 0.05734419428571429, "hi": 0.057807234285714285, "mid": 0.057575714285714286, "touches": 7, "hours_ago": 7, "sources": ["1d", "1h", "4h"]}, {"lo": 0.056311813333333335, "hi": 0.05677485333333333, "mid": 0.056543333333333334, "touches": 3, "hours_ago": 3, "sources": ["1h", "4h"]}, {"lo": 0.05259514666666667, "hi": 0.05305818666666667, "mid": 0.05282666666666667, "touches": 3, "hours_ago": 48, "sources": ["1d", "4h"]}, {"lo": 0.04798848, "hi": 0.04845152, "mid": 0.04822, "touches": 2, "hours_ago": 432, "sources": ["1d", "4h"]}, {"lo": 0.04086848, "hi": 0.04133152, "mid": 0.0411, "touches": 2, "hours_ago": 696, "sources": ["1d", "4h"]}]}, "block5_checklist": {"items": [["Тренд старшего ТФ (1D) совпадает с направлением", true], ["Свежий свип ликвидности в пользу направления", true], ["Цена у зоны интереса (не в вакууме)", false], ["Killzone активна или близко", true], ["Funding не против позиции", true], ["R:R по структуре ≥ 1:1.5", false]], "score": 4}, "block6_liquidity": {"sweep_1h": {"type": "sweep_high", "level": 0.06084, "bars_ago": 11, "volume_confirmed": false}, "sweep_4h": {"type": "sweep_high", "level": 0.06122, "bars_ago": 3, "volume_confirmed": false}, "equal_levels": [{"price": 0.057415, "kind": "low", "touches": 2}, {"price": 0.05767, "kind": "low", "touches": 3}, {"price": 0.06146, "kind": "low", "touches": 2}]}, "block7_oi": {"oi_change_pct": 0.0, "oi_combo": null, "funding": null, "ls_ratio": 2.01}, "block8_killzone": {"active": {"name": "🇺🇸 NY Open", "start": 840, "end": 1020, "quality": "A", "desc": "Продолжение дневного диапазона, часто коррекция после Лондона", "remaining_min": 91}, "next": {"name": "🇬🇧 Лондон Close", "start": 1020, "end": 1140, "quality": "B", "desc": "Закрытие Лондона -- два источника, точная граница расходится (см. докстринг)", "in_min": 91}, "is_good": true, "hour": 15, "all_zones": [{"name": "🌏 Азиатская сессия", "start": 0, "end": 480, "quality": "B", "desc": "Низкая волатильность, часто рендж или хай/лоу дня"}, {"name": "🇬🇧 Лондон Open", "start": 540, "end": 720, "quality": "A+", "desc": "Наибольшие объёмы дня, ищем хай/лоу дня"}, {"name": "🇺🇸 NY Open", "start": 840, "end": 1020, "quality": "A", "desc": "Продолжение дневного диапазона, часто коррекция после Лондона", "remaining_min": 91}, {"name": "🇬🇧 Лондон Close", "start": 1020, "end": 1140, "quality": "B", "desc": "Закрытие Лондона -- два источника, точная граница расходится (см. докстринг)"}, {"name": "🇺🇸 NY Close", "start": 1380, "end": 1440, "quality": "C", "desc": "Закрытие Нью-Йорка, не подтверждено источником"}]}, "block9_phase": {"phase": "Маркап (Markup)", "note": "объём: доступен, но не используется в этой упрощённой эвристике"}, "block10_dca": {"entry1": 0.05824, "entry2": 0.058875, "entry3": 0.05951, "weights": "50/30/20"}, "block11_tp_rr": {"tp1": 0.057575714285714286, "tp2": 0.056543333333333334, "tp3": 0.05282666666666667, "rr_tp1": 0.24, "rr_tp2": 0.62, "rr_tp3": 1.96, "rr_gate_pass": false}, "block12_sl": {"sl": 0.060997749999999996, "buffer_pct": 2.5}, "block13_verdict": {"has_setup": false, "direction": "short", "score": 4, "text": "шорт: сетапа нет (чеклист 4/6), тип сетапа: AMD — фаза distribution_bear (цена below NY-midnight)"}, "direction": "short", "score": 4, "entry_zone": {"lo": 0.05824, "hi": 0.05951}, "sl": 0.060997749999999996, "tp1": 0.057575714285714286, "tp2": 0.056543333333333334, "tp3": 0.05282666666666667, "setup_type": "AMD"}, "tz13_score": 4, "tz13_direction": "short", "tz13_setup_type": "AMD", "tz13_entry_zone": {"lo": 0.05824, "hi": 0.05951}, "tz13_sl": 0.060997749999999996, "tz13_tp1": 0.057575714285714286, "tz13_tp2": 0.056543333333333334, "tz13_tp3": 0.05282666666666667, "sweep_1h": {"type": "sweep_high", "level": 0.06084, "bars_ago": 11, "volume_confirmed": false}, "sweep_4h": {"type": "sweep_high", "level": 0.06122, "bars_ago": 3, "volume_confirmed": false}, "source": "send_scheduled", "promoted_live": false, "gate_reasons": ["rocket_or_grade", "rr_gate"], "oi_funding_ls_shadow": {"oi_change_pct": 0.0, "oi_combo": null, "funding_rate": 0.0155, "ls_ratio": 2.01, "d_oi": 0, "d_funding": 0, "d_ls": 3, "total_delta": 3, "rocket_old": 50, "rocket_would_be": 53}, "bos_body_close_shadow": {"wick_only_type": "CHoCH_bull", "body_close_type": "invalid_break_wick_only", "disagree": true, "downgraded_to_invalid": true, "body_close_label": "Пробой вверх только тенью, без закрытия за уровнем 0.06122 -- по критерию \"Урок 2. Structure\" это SFP, не валидный слом структуры"}, "order_block_shadow": {"live": {"bull": false, "bull_zone": null, "bear": false, "bear_zone": null}, "methodology": {"bull": false, "bull_zone": null, "bear": false, "bear_zone": null}}}, {"ts": 1784292223.309494, "symbol": "DOT", "direction": "short", "entry_lo": 0.8475, "entry_hi": 0.9075, "sl": 0.9301875, "tp1": 0.682125, "tp2": 0.5829, "tp3": 0.4340625, "rr_tp1_live": 2.0, "shadow_rr_gate_pass": true, "breaker_mitigation": "mitigation", "divergence": {"bearish_classical": false, "bearish_hidden": false, "bullish_classical": false, "bullish_hidden": false}, "bpr_zone_count": 10, "bpr_confluence": true, "whale_klvl_confluence": false, "whale_klvl_matches": [], "amd_phase_methodology": {"phase": "distribution_bear", "nymidnight_price": 0.8489, "price_vs_nymidnight": "below"}, "inducement": {"inducement_swept": true, "detail": {"type": "sweep_high", "level": 0.8681, "bars_ago": 4, "volume_confirmed": true}}, "order_block_live": {"bull": true, "bull_zone": [0.8435, 0.8454], "bear": false, "bear_zone": null}, "order_block_methodology": {"bull": true, "bull_zone": [0.8281, 0.8435], "bear": false, "bear_zone": null}, "chart_patterns": {"flag": {"bull": false, "bear": false, "target": null}, "head_shoulders": {"top": true, "bottom": false, "target": 0.7917999999999998}, "triangle": {"type": null}}, "patches_affected": ["03-breaker-mitigation", "05-bpr"], "discrepancy": ["bpr: зона входа пересекается со свежим BPR (confluence)"], "live_journal_id": 305, "tz13_shadow": {}, "tz13_score": null, "tz13_direction": null, "tz13_setup_type": null, "tz13_entry_zone": null, "tz13_sl": null, "tz13_tp1": null, "tz13_tp2": null, "tz13_tp3": null, "sweep_1h": {"type": "sweep_low", "level": 0.8434, "bars_ago": 4, "volume_confirmed": false}, "sweep_4h": {"type": "sweep_high", "level": 0.8681, "bars_ago": 4, "volume_confirmed": true}}, {"ts": 1784292288.603863, "symbol": "SEI", "direction": "short", "entry_lo": 0.04695, "entry_hi": 0.04795, "sl": 0.04914875, "tp1": 0.0425525, "tp2": 0.039914, "tp3": 0.03595625, "rr_tp1_live": 2.0, "shadow_rr_gate_pass": true, "breaker_mitigation": "mitigation", "divergence": {"bearish_classical": true, "bearish_hidden": false, "bullish_classical": false, "bullish_hidden": false}, "bpr_zone_count": 7, "bpr_confluence": false, "whale_klvl_confluence": false, "whale_klvl_matches": [], "amd_phase_methodology": {"phase": "distribution_bull", "nymidnight_price": 0.04654, "price_vs_nymidnight": "above"}, "inducement": {"inducement_swept": true, "detail": {"type": "sweep_high", "level": 0.04923, "bars_ago": 10, "volume_confirmed": true}}, "order_block_live": {"bull": false, "bull_zone": null, "bear": false, "bear_zone": null}, "order_block_methodology": {"bull": false, "bull_zone": null, "bear": false, "bear_zone": null}, "chart_patterns": {"flag": {"bull": false, "bear": false, "target": null}, "head_shoulders": {"top": true, "bottom": false, "target": 0.04609}, "triangle": {"type": "descending"}}, "patches_affected": ["03-breaker-mitigation"], "discrepancy": [], "live_journal_id": 307, "tz13_shadow": {}, "tz13_score": null, "tz13_direction": null, "tz13_setup_type": null, "tz13_entry_zone": null, "tz13_sl": null, "tz13_tp1": null, "tz13_tp2": null, "tz13_tp3": null, "sweep_1h": null, "sweep_4h": {"type": "sweep_high", "level": 0.04923, "bars_ago": 10, "volume_confirmed": true}}, {"ts": 1784292345.4545236, "symbol": "PIEVERSE", "direction": "long", "entry_lo": 0.6261216, "entry_hi": 0.6314784, "sl": 0.61046856, "tp1": 0.66994815, "tp2": 0.67730023, "tp3": 0.7170825, "rr_tp1_live": 1.83, "shadow_rr_gate_pass": false, "breaker_mitigation": "mitigation", "divergence": {"bearish_classical": false, "bearish_hidden": false, "bullish_classical": false, "bullish_hidden": false}, "bpr_zone_count": 8, "bpr_confluence": false, "whale_klvl_confluence": false, "whale_klvl_matches": [], "amd_phase_methodology": {"phase": "distribution_bull", "nymidnight_price": 0.6485, "price_vs_nymidnight": "above"}, "inducement": {"inducement_swept": true, "detail": {"type": "sweep_low", "level": 0.6593, "bars_ago": 11, "volume_confirmed": false}}, "order_block_live": {"bull": false, "bull_zone": null, "bear": true, "bear_zone": [0.6742, 0.6742]}, "order_block_methodology": {"bull": false, "bull_zone": null, "bear": true, "bear_zone": [0.6742, 0.6923]}, "chart_patterns": {"flag": {"bull": false, "bear": false, "target": null}, "head_shoulders": {"top": true, "bottom": false, "target": 0.6127}, "triangle": {"type": null}}, "patches_affected": ["02-rr-gate", "03-breaker-mitigation"], "discrepancy": ["rr_gate: R:R 1.83 прошёл live-гейт (1.5), но НЕ прошёл бы shadow-гейт (2.0)"], "live_journal_id": 309, "tz13_shadow": {}, "tz13_score": null, "tz13_direction": null, "tz13_setup_type": null, "tz13_entry_zone": null, "tz13_sl": null, "tz13_tp1": null, "tz13_tp2": null, "tz13_tp3": null, "sweep_1h": {"type": "sweep_high", "level": 0.6682, "bars_ago": 9, "volume_confirmed": true}, "sweep_4h": {"type": "sweep_low", "level": 0.6593, "bars_ago": 11, "volume_confirmed": false}}, {"ts": 1784292387.5825849, "symbol": "BERA", "direction": "short", "entry_lo": 0.1845, "entry_hi": 0.1969, "sl": 0.2018225, "tp1": 0.149855, "tp2": 0.129068, "tp3": 0.0978875, "rr_tp1_live": 2.0, "shadow_rr_gate_pass": true, "breaker_mitigation": "mitigation", "divergence": {"bearish_classical": false, "bearish_hidden": false, "bullish_classical": true, "bullish_hidden": false}, "bpr_zone_count": 0, "bpr_confluence": false, "whale_klvl_confluence": false, "whale_klvl_matches": [], "amd_phase_methodology": {"phase": "distribution_bear", "nymidnight_price": 0.1861, "price_vs_nymidnight": "below"}, "inducement": {"inducement_swept": true, "detail": {"type": "sweep_low", "level": 0.1857, "bars_ago": 7, "volume_confirmed": false}}, "order_block_live": {"bull": false, "bull_zone": null, "bear": false, "bear_zone": null}, "order_block_methodology": {"bull": false, "bull_zone": null, "bear": false, "bear_zone": null}, "chart_patterns": {"flag": {"bull": false, "bear": false, "target": null}, "head_shoulders": {"top": true, "bottom": false, "target": 0.17250000000000004}, "triangle": {"type": null}}, "patches_affected": ["03-breaker-mitigation", "04-rsi-divergence"], "discrepancy": ["divergence: классическая дивергенция ПРОТИВ направления сигнала"], "live_journal_id": 311, "tz13_shadow": {}, "tz13_score": null, "tz13_direction": null, "tz13_setup_type": null, "tz13_entry_zone": null, "tz13_sl": null, "tz13_tp1": null, "tz13_tp2": null, "tz13_tp3": null, "sweep_1h": {"type": "sweep_high", "level": 0.1885, "bars_ago": 6, "volume_confirmed": true}, "sweep_4h": {"type": "sweep_low", "level": 0.1857, "bars_ago": 7, "volume_confirmed": false}}, {"ts": 1784292453.492323, "symbol": "VELVET", "direction": "short", "entry_lo": 0.57124, "entry_hi": 0.5773, "sl": 0.5917325, "tp1": 0.53776286, "tp2": 0.52334833, "tp3": 0.50143182, "rr_tp1_live": 1.63, "shadow_rr_gate_pass": false, "breaker_mitigation": "mitigation", "divergence": {"bearish_classical": false, "bearish_hidden": false, "bullish_classical": false, "bullish_hidden": true}, "bpr_zone_count": 6, "bpr_confluence": false, "whale_klvl_confluence": false, "whale_klvl_matches": [], "amd_phase_methodology": {"phase": "distribution_bull", "nymidnight_price": 0.52559, "price_vs_nymidnight": "above"}, "inducement": {"inducement_swept": true, "detail": {"type": "sweep_low", "level": 0.5, "bars_ago": 8, "volume_confirmed": false}}, "order_block_live": {"bull": false, "bull_zone": null, "bear": false, "bear_zone": null}, "order_block_methodology": {"bull": false, "bull_zone": null, "bear": true, "bear_zone": [0.55302, 0.58968]}, "chart_patterns": {"flag": {"bull": true, "bear": false, "target": 0.79462}, "head_shoulders": {"top": true, "bottom": false, "target": 0.36475}, "triangle": {"type": null}}, "patches_affected": ["02-rr-gate", "03-breaker-mitigation", "07-order-block-body"], "discrepancy": ["rr_gate: R:R 1.63 прошёл live-гейт (1.5), но НЕ прошёл бы shadow-гейт (2.0)", "order_block: live(bull=False,bear=False) vs methodology-тело(bull=False,bear=True)"], "live_journal_id": 313, "tz13_shadow": {}, "tz13_score": null, "tz13_direction": null, "tz13_setup_type": null, "tz13_entry_zone": null, "tz13_sl": null, "tz13_tp1": null, "tz13_tp2": null, "tz13_tp3": null, "sweep_1h": null, "sweep_4h": {"type": "sweep_low", "level": 0.5, "bars_ago": 8, "volume_confirmed": false}}]}