{"schema_version": 1, "records": [{"ts": 1784257028.1648958, "symbol": "TRUMP", "direction": "short", "entry_lo": 1.536, "entry_hi": 1.632, "sl": 1.6728, "tp1": 1.2624, "tp2": 1.09824, "tp3": 0.852, "rr_tp1_live": 2.0, "shadow_rr_gate_pass": true, "breaker_mitigation": "mitigation", "divergence": {"bearish_classical": false, "bearish_hidden": false, "bullish_classical": false, "bullish_hidden": false}, "bpr_zone_count": 6, "bpr_confluence": false, "whale_klvl_confluence": false, "whale_klvl_matches": [], "amd_phase_methodology": {"phase": "accumulation", "nymidnight_price": 1.566, "price_vs_nymidnight": "below"}, "inducement": {"inducement_swept": true, "detail": {"type": "sweep_high", "level": 1.566, "bars_ago": 11, "volume_confirmed": false}}, "order_block_live": {"bull": false, "bull_zone": null, "bear": false, "bear_zone": null}, "order_block_methodology": {"bull": false, "bull_zone": null, "bear": false, "bear_zone": null}, "chart_patterns": {"flag": {"bull": false, "bear": false, "target": null}, "head_shoulders": {"top": true, "bottom": false, "target": 1.5080000000000002}, "triangle": {"type": null}}, "patches_affected": ["03-breaker-mitigation"], "discrepancy": [], "live_journal_id": 286, "tz13_shadow": {"ok": true, "block1_bias": {"bias": "SHORT", "structure_1d": "LH/LL (даунтренд)", "tf_agreement": "1D и 4H согласованы", "detail": ["1D структура: LH/LL (даунтренд)", "4H EMA-стек: медвежий", "1H EMA-стек (контекст входа): недостаточно данных", "Ключевой минимум: 1.51 (пробой = предпосылка разворота/продолжения вниз)", "Ключевой хай: 1.602 (снятие = цель движения вверх)"], "key_low": {"price": 1.51, "bars_ago": 4}, "key_high": {"price": 1.602, "bars_ago": 2}}, "block2_elliott": {"elliott_1d": {"wave": "2", "label": "похоже на волну 2 (коррекция перед волной 3)", "note": "потенциальный вход у завершения коррекции", "score_delta": 5}, "elliott_4h": {"wave": null, "label": "волна не определена", "note": "структура неоднозначная", "score_delta": 0}}, "block3_setup_type": {"setup_type": "Sweep", "label": "Liquidity Sweep — sweep_high (11 баров назад), без подтверждённого BOS", "detail": {"type": "sweep_high", "level": 1.566, "bars_ago": 11, "volume_confirmed": false}}, "block4_zones": {"above": [{"lo": 1.536, "hi": 1.632, "mid": 1.5782553191489368, "touches": 47, "hours_ago": 3, "sources": ["1d", "1h", "4h"]}, {"lo": 1.577748211644955, "hi": 1.590036211644955, "mid": 1.583892211644955, "touches": 1, "hours_ago": 0, "sources": ["ema"]}, {"lo": 1.6260496329825191, "hi": 1.638337632982519, "mid": 1.632193632982519, "touches": 1, "hours_ago": 0, "sources": ["ema"]}, {"lo": 1.662, "hi": 1.691, "mid": 1.6766666666666667, "touches": 6, "hours_ago": 224, "sources": ["4h"]}, {"lo": 1.706, "hi": 1.758, "mid": 1.7304166666666667, "touches": 12, "hours_ago": 244, "sources": ["1d", "4h"]}, {"lo": 1.7276898167584904, "hi": 1.7399778167584903, "mid": 1.7338338167584904, "touches": 1, "hours_ago": 0, "sources": ["ema"]}, {"lo": 1.776, "hi": 1.794, "mid": 1.7828, "touches": 5, "hours_ago": 556, "sources": ["1d", "4h"]}, {"lo": 1.873856, "hi": 1.888, "mid": 1.88, "touches": 3, "hours_ago": 296, "sources": ["1d", "4h"]}, {"lo": 1.9548560000000001, "hi": 1.967144, "mid": 1.961, "touches": 3, "hours_ago": 600, "sources": ["4h"]}, {"lo": 2.002856, "hi": 2.015144, "mid": 2.009, "touches": 2, "hours_ago": 612, "sources": ["1d", "4h"]}], "below": []}, "block5_checklist": {"items": [["Тренд старшего ТФ (1D) совпадает с направлением", true], ["Свежий свип ликвидности в пользу направления", true], ["Цена у зоны интереса (не в вакууме)", false], ["Killzone активна или близко", false], ["Funding не против позиции", true], ["R:R по структуре ≥ 1:1.5", true]], "score": 4}, "block6_liquidity": {"sweep_1h": null, "sweep_4h": {"type": "sweep_high", "level": 1.566, "bars_ago": 11, "volume_confirmed": false}, "equal_levels": [{"price": 1.6284999999999998, "kind": "high", "touches": 4}, {"price": 1.6825, "kind": "high", "touches": 2}, {"price": 1.72475, "kind": "high", "touches": 4}, {"price": 1.7363333333333333, "kind": "high", "touches": 3}, {"price": 1.9605000000000001, "kind": "high", "touches": 2}, {"price": 1.542, "kind": "low", "touches": 2}, {"price": 1.5890000000000002, "kind": "low", "touches": 3}, {"price": 1.5990000000000002, "kind": "low", "touches": 2}, {"price": 1.6305, "kind": "low", "touches": 2}, {"price": 1.664, "kind": "low", "touches": 2}, {"price": 1.792, "kind": "low", "touches": 2}]}, "block7_oi": {"oi_change_pct": 0.0, "oi_combo": null, "funding": null, "ls_ratio": 3.08}, "block8_killzone": {"active": {"name": "🌏 Азиатская сессия", "start": 0, "end": 480, "quality": "B", "desc": "Низкая волатильность, часто рендж или хай/лоу дня", "remaining_min": 123}, "next": {"name": "🇬🇧 Лондон Open", "start": 540, "end": 720, "quality": "A+", "desc": "Наибольшие объёмы дня, ищем хай/лоу дня", "in_min": 183}, "is_good": false, "hour": 5, "all_zones": [{"name": "🌏 Азиатская сессия", "start": 0, "end": 480, "quality": "B", "desc": "Низкая волатильность, часто рендж или хай/лоу дня", "remaining_min": 123}, {"name": "🇬🇧 Лондон Open", "start": 540, "end": 720, "quality": "A+", "desc": "Наибольшие объёмы дня, ищем хай/лоу дня"}, {"name": "🇺🇸 NY Open", "start": 840, "end": 1020, "quality": "A", "desc": "Продолжение дневного диапазона, часто коррекция после Лондона"}, {"name": "🇬🇧 Лондон Close", "start": 1020, "end": 1140, "quality": "B", "desc": "Закрытие Лондона -- два источника, точная граница расходится (см. докстринг)"}, {"name": "🇺🇸 NY Close", "start": 1380, "end": 1440, "quality": "C", "desc": "Закрытие Нью-Йорка, не подтверждено источником"}]}, "block9_phase": {"phase": "Маркдаун (Markdown)", "note": "объём: доступен, но не используется в этой упрощённой эвристике"}, "block10_dca": {"entry1": 1.536, "entry2": 1.584, "entry3": 1.632, "weights": "50/30/20"}, "block11_tp_rr": {"tp1": 1.2624000000000004, "tp2": 1.0982400000000005, "tp3": 0.852000000000001, "rr_tp1": 2.0, "rr_tp2": 3.2, "rr_tp3": 5.0, "rr_gate_pass": true}, "block12_sl": {"sl": 1.6727999999999998, "buffer_pct": 2.5}, "block13_verdict": {"has_setup": true, "direction": "short", "score": 4, "text": "шорт: сетап готов (чеклист 4/6), тип сетапа: Liquidity Sweep — sweep_high (11 баров назад), без подтверждённого BOS"}, "direction": "short", "score": 4, "entry_zone": {"lo": 1.536, "hi": 1.632}, "sl": 1.6727999999999998, "tp1": 1.2624000000000004, "tp2": 1.0982400000000005, "tp3": 0.852000000000001, "setup_type": "Sweep"}, "tz13_score": 4, "tz13_direction": "short", "tz13_setup_type": "Sweep", "tz13_entry_zone": {"lo": 1.536, "hi": 1.632}, "tz13_sl": 1.6727999999999998, "tz13_tp1": 1.2624000000000004, "tz13_tp2": 1.0982400000000005, "tz13_tp3": 0.852000000000001, "sweep_1h": null, "sweep_4h": {"type": "sweep_high", "level": 1.566, "bars_ago": 11, "volume_confirmed": false}, "source": "send_scheduled", "promoted_live": true, "gate_reasons": [], "oi_funding_ls_shadow": {"oi_change_pct": 0.0, "oi_combo": null, "funding_rate": -0.004211, "ls_ratio": 3.08, "d_oi": 0, "d_funding": 0, "d_ls": 3, "total_delta": 3, "rocket_old": 64, "rocket_would_be": 67}, "bos_body_close_shadow": {"wick_only_type": null, "body_close_type": null, "disagree": false, "downgraded_to_invalid": false, "body_close_label": "структура не определена"}, "order_block_shadow": {"live": {"bull": false, "bull_zone": null, "bear": false, "bear_zone": null}, "methodology": {"bull": false, "bull_zone": null, "bear": false, "bear_zone": null}}}]}